[
  {
    "id": "IO012018_Sagar",
    "dead_or_missing": 79,
    "cost_usd": 30000000,
    "retired": false,
    "data": [
      {
        "date": "20180515",
        "time_utc": "1800",
        "record": null,
        "status": "DB",
        "lat": 11.3,
        "lng": 53.7,
        "max_wind_kt": 20,
        "min_pressure_mb": 1007,
        "34kt_wind_nm": {
          "ne": 0,
          "se": 0,
          "sw": 0,
          "nw": 0
        },
        "50kt_wind_nm": {
          "ne": 0,
          "se": 0,
          "sw": 0,
          "nw": 0
        },
        "64kt_wind_nm": {
          "ne": 0,
          "se": 0,
          "sw": 0,
          "nw": 0
        }
      },
      {
        "date": "20180516",
        "time_utc": "0000",
        "record": null,
        "status": "TD",
        "lat": 12,
        "lng": 52.7,
        "max_wind_kt": 25,
        "min_pressure_mb": 1004,
        "34kt_wind_nm": {
          "ne": 0,
          "se": 0,
          "sw": 0,
          "nw": 0
        },
        "50kt_wind_nm": {
          "ne": 0,
          "se": 0,
          "sw": 0,
          "nw": 0
        },
        "64kt_wind_nm": {
          "ne": 0,
          "se": 0,
          "sw": 0,
          "nw": 0
        }
      },
      {
        "date": "20180516",
        "time_utc": "0600",
        "record": null,
        "status": "TD",
        "lat": 12.7,
        "lng": 51.6,
        "max_wind_kt": 25,
        "min_pressure_mb": 1004,
        "34kt_wind_nm": {
          "ne": 0,
          "se": 0,
          "sw": 0,
          "nw": 0
        },
        "50kt_wind_nm": {
          "ne": 0,
          "se": 0,
          "sw": 0,
          "nw": 0
        },
        "64kt_wind_nm": {
          "ne": 0,
          "se": 0,
          "sw": 0,
          "nw": 0
        }
      },
      {
        "date": "20180516",
        "time_utc": "1200",
        "record": null,
        "status": "TD",
        "lat": 13.1,
        "lng": 50.6,
        "max_wind_kt": 30,
        "min_pressure_mb": 1005,
        "34kt_wind_nm": {
          "ne": 0,
          "se": 0,
          "sw": 0,
          "nw": 0
        },
        "50kt_wind_nm": {
          "ne": 0,
          "se": 0,
          "sw": 0,
          "nw": 0
        },
        "64kt_wind_nm": {
          "ne": 0,
          "se": 0,
          "sw": 0,
          "nw": 0
        }
      },
      {
        "date": "20180516",
        "time_utc": "1800",
        "record": null,
        "status": "TS",
        "lat": 13.2,
        "lng": 49.7,
        "max_wind_kt": 35,
        "min_pressure_mb": 1002,
        "34kt_wind_nm": {
          "ne": 0,
          "se": 30,
          "sw": 40,
          "nw": 50
        },
        "50kt_wind_nm": {
          "ne": 0,
          "se": 0,
          "sw": 0,
          "nw": 0
        },
        "64kt_wind_nm": {
          "ne": 0,
          "se": 0,
          "sw": 0,
          "nw": 0
        }
      },
      {
        "date": "20180517",
        "time_utc": "0000",
        "record": null,
        "status": "TS",
        "lat": 13.2,
        "lng": 49.3,
        "max_wind_kt": 40,
        "min_pressure_mb": 1002,
        "34kt_wind_nm": {
          "ne": 35,
          "se": 35,
          "sw": 45,
          "nw": 65
        },
        "50kt_wind_nm": {
          "ne": 0,
          "se": 0,
          "sw": 0,
          "nw": 0
        },
        "64kt_wind_nm": {
          "ne": 0,
          "se": 0,
          "sw": 0,
          "nw": 0
        }
      },
      {
        "date": "20180517",
        "time_utc": "0600",
        "record": null,
        "status": "TS",
        "lat": 13.2,
        "lng": 48.9,
        "max_wind_kt": 45,
        "min_pressure_mb": 989,
        "34kt_wind_nm": {
          "ne": 40,
          "se": 40,
          "sw": 50,
          "nw": 70
        },
        "50kt_wind_nm": {
          "ne": 0,
          "se": 0,
          "sw": 0,
          "nw": 0
        },
        "64kt_wind_nm": {
          "ne": 0,
          "se": 0,
          "sw": 0,
          "nw": 0
        }
      },
      {
        "date": "20180517",
        "time_utc": "1200",
        "record": null,
        "status": "TS",
        "lat": 13,
        "lng": 48.1,
        "max_wind_kt": 50,
        "min_pressure_mb": 985,
        "34kt_wind_nm": {
          "ne": 45,
          "se": 40,
          "sw": 50,
          "nw": 75
        },
        "50kt_wind_nm": {
          "ne": 0,
          "se": 0,
          "sw": 0,
          "nw": 0
        },
        "64kt_wind_nm": {
          "ne": 0,
          "se": 0,
          "sw": 0,
          "nw": 0
        }
      },
      {
        "date": "20180517",
        "time_utc": "1800",
        "record": null,
        "status": "TS",
        "lat": 12.4,
        "lng": 47,
        "max_wind_kt": 50,
        "min_pressure_mb": 985,
        "34kt_wind_nm": {
          "ne": 45,
          "se": 40,
          "sw": 40,
          "nw": 80
        },
        "50kt_wind_nm": {
          "ne": 0,
          "se": 0,
          "sw": 0,
          "nw": 0
        },
        "64kt_wind_nm": {
          "ne": 0,
          "se": 0,
          "sw": 0,
          "nw": 0
        }
      },
      {
        "date": "20180518",
        "time_utc": "0000",
        "record": null,
        "status": "TS",
        "lat": 11.9,
        "lng": 46.4,
        "max_wind_kt": 50,
        "min_pressure_mb": 985,
        "34kt_wind_nm": {
          "ne": 90,
          "se": 55,
          "sw": 50,
          "nw": 80
        },
        "50kt_wind_nm": {
          "ne": 20,
          "se": 20,
          "sw": 20,
          "nw": 30
        },
        "64kt_wind_nm": {
          "ne": 0,
          "se": 0,
          "sw": 0,
          "nw": 0
        }
      },
      {
        "date": "20180518",
        "time_utc": "0600",
        "record": null,
        "status": "TS",
        "lat": 11.7,
        "lng": 45.9,
        "max_wind_kt": 55,
        "min_pressure_mb": 982,
        "34kt_wind_nm": {
          "ne": 95,
          "se": 55,
          "sw": 50,
          "nw": 80
        },
        "50kt_wind_nm": {
          "ne": 35,
          "se": 25,
          "sw": 20,
          "nw": 30
        },
        "64kt_wind_nm": {
          "ne": 0,
          "se": 0,
          "sw": 0,
          "nw": 0
        }
      },
      {
        "date": "20180518",
        "time_utc": "1200",
        "record": null,
        "status": "TS",
        "lat": 11.5,
        "lng": 45.5,
        "max_wind_kt": 60,
        "min_pressure_mb": 978,
        "34kt_wind_nm": {
          "ne": 75,
          "se": 45,
          "sw": 45,
          "nw": 65
        },
        "50kt_wind_nm": {
          "ne": 15,
          "se": 10,
          "sw": 15,
          "nw": 20
        },
        "64kt_wind_nm": {
          "ne": 0,
          "se": 0,
          "sw": 0,
          "nw": 0
        }
      },
      {
        "date": "20180518",
        "time_utc": "1800",
        "record": null,
        "status": "CY",
        "lat": 11.2,
        "lng": 45.1,
        "max_wind_kt": 65,
        "min_pressure_mb": 974,
        "34kt_wind_nm": {
          "ne": 50,
          "se": 45,
          "sw": 40,
          "nw": 45
        },
        "50kt_wind_nm": {
          "ne": 10,
          "se": 20,
          "sw": 25,
          "nw": 20
        },
        "64kt_wind_nm": {
          "ne": 0,
          "se": 0,
          "sw": 0,
          "nw": 0
        }
      },
      {
        "date": "20180519",
        "time_utc": "0000",
        "record": null,
        "status": "TS",
        "lat": 10.9,
        "lng": 44.7,
        "max_wind_kt": 60,
        "min_pressure_mb": 978,
        "34kt_wind_nm": {
          "ne": 55,
          "se": 45,
          "sw": 50,
          "nw": 60
        },
        "50kt_wind_nm": {
          "ne": 20,
          "se": 15,
          "sw": 15,
          "nw": 25
        },
        "64kt_wind_nm": {
          "ne": 0,
          "se": 0,
          "sw": 0,
          "nw": 0
        }
      },
      {
        "date": "20180519",
        "time_utc": "0600",
        "record": null,
        "status": "TS",
        "lat": 10.6,
        "lng": 44.3,
        "max_wind_kt": 55,
        "min_pressure_mb": 982,
        "34kt_wind_nm": {
          "ne": 55,
          "se": 45,
          "sw": 45,
          "nw": 55
        },
        "50kt_wind_nm": {
          "ne": 30,
          "se": 30,
          "sw": 30,
          "nw": 30
        },
        "64kt_wind_nm": {
          "ne": 0,
          "se": 0,
          "sw": 0,
          "nw": 0
        }
      },
      {
        "date": "20180519",
        "time_utc": "1200",
        "record": "L",
        "status": "TS",
        "lat": 10.3,
        "lng": 43.9,
        "max_wind_kt": 50,
        "min_pressure_mb": 995,
        "34kt_wind_nm": {
          "ne": 55,
          "se": 40,
          "sw": 40,
          "nw": 55
        },
        "50kt_wind_nm": {
          "ne": 25,
          "se": 20,
          "sw": 20,
          "nw": 25
        },
        "64kt_wind_nm": {
          "ne": 0,
          "se": 0,
          "sw": 0,
          "nw": 0
        }
      },
      {
        "date": "20180519",
        "time_utc": "1800",
        "record": null,
        "status": "TS",
        "lat": 10,
        "lng": 43.5,
        "max_wind_kt": 45,
        "min_pressure_mb": 989,
        "34kt_wind_nm": {
          "ne": 50,
          "se": 45,
          "sw": 50,
          "nw": 55
        },
        "50kt_wind_nm": {
          "ne": 0,
          "se": 0,
          "sw": 0,
          "nw": 0
        },
        "64kt_wind_nm": {
          "ne": 0,
          "se": 0,
          "sw": 0,
          "nw": 0
        }
      },
      {
        "date": "20180520",
        "time_utc": "0000",
        "record": null,
        "status": "TS",
        "lat": 9.9,
        "lng": 42.8,
        "max_wind_kt": 40,
        "min_pressure_mb": 993,
        "34kt_wind_nm": {
          "ne": 50,
          "se": 45,
          "sw": 45,
          "nw": 50
        },
        "50kt_wind_nm": {
          "ne": 0,
          "se": 0,
          "sw": 0,
          "nw": 0
        },
        "64kt_wind_nm": {
          "ne": 0,
          "se": 0,
          "sw": 0,
          "nw": 0
        }
      },
      {
        "date": "20180520",
        "time_utc": "0600",
        "record": null,
        "status": "TD",
        "lat": 9.8,
        "lng": 41.8,
        "max_wind_kt": 30,
        "min_pressure_mb": 1000,
        "34kt_wind_nm": {
          "ne": 0,
          "se": 0,
          "sw": 0,
          "nw": 0
        },
        "50kt_wind_nm": {
          "ne": 0,
          "se": 0,
          "sw": 0,
          "nw": 0
        },
        "64kt_wind_nm": {
          "ne": 0,
          "se": 0,
          "sw": 0,
          "nw": 0
        }
      }
    ]
  },
  {
    "id": "IO022018_Mekunu",
    "dead_or_missing": 31,
    "cost_usd": 1500000000,
    "retired": false,
    "data": [
      {
        "date": "20180521",
        "time_utc": "0600",
        "record": null,
        "status": "TD",
        "lat": 7.9,
        "lng": 58.6,
        "max_wind_kt": 25,
        "min_pressure_mb": 1004,
        "34kt_wind_nm": {
          "ne": 0,
          "se": 0,
          "sw": 0,
          "nw": 0
        },
        "50kt_wind_nm": {
          "ne": 0,
          "se": 0,
          "sw": 0,
          "nw": 0
        },
        "64kt_wind_nm": {
          "ne": 0,
          "se": 0,
          "sw": 0,
          "nw": 0
        }
      },
      {
        "date": "20180521",
        "time_utc": "1200",
        "record": null,
        "status": "TD",
        "lat": 8.3,
        "lng": 58.2,
        "max_wind_kt": 25,
        "min_pressure_mb": 1004,
        "34kt_wind_nm": {
          "ne": 0,
          "se": 0,
          "sw": 0,
          "nw": 0
        },
        "50kt_wind_nm": {
          "ne": 0,
          "se": 0,
          "sw": 0,
          "nw": 0
        },
        "64kt_wind_nm": {
          "ne": 0,
          "se": 0,
          "sw": 0,
          "nw": 0
        }
      },
      {
        "date": "20180521",
        "time_utc": "1800",
        "record": null,
        "status": "TD",
        "lat": 8.7,
        "lng": 57.8,
        "max_wind_kt": 30,
        "min_pressure_mb": 1003,
        "34kt_wind_nm": {
          "ne": 0,
          "se": 0,
          "sw": 0,
          "nw": 0
        },
        "50kt_wind_nm": {
          "ne": 0,
          "se": 0,
          "sw": 0,
          "nw": 0
        },
        "64kt_wind_nm": {
          "ne": 0,
          "se": 0,
          "sw": 0,
          "nw": 0
        }
      },
      {
        "date": "20180522",
        "time_utc": "0000",
        "record": null,
        "status": "TS",
        "lat": 9.1,
        "lng": 57.5,
        "max_wind_kt": 35,
        "min_pressure_mb": 999,
        "34kt_wind_nm": {
          "ne": 90,
          "se": 125,
          "sw": 95,
          "nw": 105
        },
        "50kt_wind_nm": {
          "ne": 0,
          "se": 0,
          "sw": 0,
          "nw": 0
        },
        "64kt_wind_nm": {
          "ne": 0,
          "se": 0,
          "sw": 0,
          "nw": 0
        }
      },
      {
        "date": "20180522",
        "time_utc": "0600",
        "record": null,
        "status": "TS",
        "lat": 9.6,
        "lng": 57.2,
        "max_wind_kt": 35,
        "min_pressure_mb": 1000,
        "34kt_wind_nm": {
          "ne": 95,
          "se": 100,
          "sw": 170,
          "nw": 140
        },
        "50kt_wind_nm": {
          "ne": 0,
          "se": 0,
          "sw": 0,
          "nw": 0
        },
        "64kt_wind_nm": {
          "ne": 0,
          "se": 0,
          "sw": 0,
          "nw": 0
        }
      },
      {
        "date": "20180522",
        "time_utc": "1200",
        "record": null,
        "status": "TS",
        "lat": 10.2,
        "lng": 56.8,
        "max_wind_kt": 40,
        "min_pressure_mb": 993,
        "34kt_wind_nm": {
          "ne": 90,
          "se": 130,
          "sw": 145,
          "nw": 120
        },
        "50kt_wind_nm": {
          "ne": 0,
          "se": 0,
          "sw": 0,
          "nw": 0
        },
        "64kt_wind_nm": {
          "ne": 0,
          "se": 0,
          "sw": 0,
          "nw": 0
        }
      },
      {
        "date": "20180522",
        "time_utc": "1800",
        "record": null,
        "status": "TS",
        "lat": 10.6,
        "lng": 56.4,
        "max_wind_kt": 50,
        "min_pressure_mb": 985,
        "34kt_wind_nm": {
          "ne": 110,
          "se": 115,
          "sw": 140,
          "nw": 125
        },
        "50kt_wind_nm": {
          "ne": 0,
          "se": 0,
          "sw": 0,
          "nw": 0
        },
        "64kt_wind_nm": {
          "ne": 0,
          "se": 0,
          "sw": 0,
          "nw": 0
        }
      },
      {
        "date": "20180523",
        "time_utc": "0000",
        "record": null,
        "status": "TS",
        "lat": 10.9,
        "lng": 56.1,
        "max_wind_kt": 55,
        "min_pressure_mb": 989,
        "34kt_wind_nm": {
          "ne": 115,
          "se": 135,
          "sw": 155,
          "nw": 130
        },
        "50kt_wind_nm": {
          "ne": 65,
          "se": 80,
          "sw": 85,
          "nw": 75
        },
        "64kt_wind_nm": {
          "ne": 0,
          "se": 0,
          "sw": 0,
          "nw": 0
        }
      },
      {
        "date": "20180523",
        "time_utc": "0600",
        "record": null,
        "status": "TS",
        "lat": 11.4,
        "lng": 56.2,
        "max_wind_kt": 60,
        "min_pressure_mb": 986,
        "34kt_wind_nm": {
          "ne": 125,
          "se": 145,
          "sw": 125,
          "nw": 130
        },
        "50kt_wind_nm": {
          "ne": 60,
          "se": 75,
          "sw": 60,
          "nw": 50
        },
        "64kt_wind_nm": {
          "ne": 0,
          "se": 0,
          "sw": 0,
          "nw": 0
        }
      },
      {
        "date": "20180523",
        "time_utc": "1200",
        "record": null,
        "status": "CY",
        "lat": 11.9,
        "lng": 56.1,
        "max_wind_kt": 65,
        "min_pressure_mb": 974,
        "34kt_wind_nm": {
          "ne": 120,
          "se": 155,
          "sw": 130,
          "nw": 110
        },
        "50kt_wind_nm": {
          "ne": 60,
          "se": 85,
          "sw": 65,
          "nw": 50
        },
        "64kt_wind_nm": {
          "ne": 25,
          "se": 25,
          "sw": 25,
          "nw": 25
        }
      },
      {
        "date": "20180523",
        "time_utc": "1800",
        "record": null,
        "status": "CY",
        "lat": 12.5,
        "lng": 55.8,
        "max_wind_kt": 75,
        "min_pressure_mb": 976,
        "34kt_wind_nm": {
          "ne": 90,
          "se": 125,
          "sw": 145,
          "nw": 110
        },
        "50kt_wind_nm": {
          "ne": 45,
          "se": 70,
          "sw": 35,
          "nw": 45
        },
        "64kt_wind_nm": {
          "ne": 30,
          "se": 40,
          "sw": 25,
          "nw": 25
        }
      },
      {
        "date": "20180524",
        "time_utc": "0000",
        "record": null,
        "status": "CY",
        "lat": 13,
        "lng": 55.7,
        "max_wind_kt": 80,
        "min_pressure_mb": 963,
        "34kt_wind_nm": {
          "ne": 175,
          "se": 195,
          "sw": 200,
          "nw": 140
        },
        "50kt_wind_nm": {
          "ne": 85,
          "se": 100,
          "sw": 105,
          "nw": 65
        },
        "64kt_wind_nm": {
          "ne": 40,
          "se": 55,
          "sw": 50,
          "nw": 30
        }
      },
      {
        "date": "20180524",
        "time_utc": "0600",
        "record": null,
        "status": "CY",
        "lat": 13.7,
        "lng": 55.6,
        "max_wind_kt": 80,
        "min_pressure_mb": 971,
        "34kt_wind_nm": {
          "ne": 175,
          "se": 195,
          "sw": 200,
          "nw": 140
        },
        "50kt_wind_nm": {
          "ne": 85,
          "se": 100,
          "sw": 105,
          "nw": 65
        },
        "64kt_wind_nm": {
          "ne": 40,
          "se": 55,
          "sw": 50,
          "nw": 30
        }
      },
      {
        "date": "20180524",
        "time_utc": "1200",
        "record": null,
        "status": "CY",
        "lat": 14.3,
        "lng": 55.4,
        "max_wind_kt": 80,
        "min_pressure_mb": 963,
        "34kt_wind_nm": {
          "ne": 175,
          "se": 195,
          "sw": 200,
          "nw": 140
        },
        "50kt_wind_nm": {
          "ne": 85,
          "se": 100,
          "sw": 105,
          "nw": 65
        },
        "64kt_wind_nm": {
          "ne": 40,
          "se": 55,
          "sw": 50,
          "nw": 30
        }
      },
      {
        "date": "20180524",
        "time_utc": "1500",
        "record": null,
        "status": "CY",
        "lat": 14.6,
        "lng": 55.2,
        "max_wind_kt": 80,
        "min_pressure_mb": 963,
        "34kt_wind_nm": {
          "ne": 130,
          "se": 195,
          "sw": 190,
          "nw": 110
        },
        "50kt_wind_nm": {
          "ne": 70,
          "se": 110,
          "sw": 105,
          "nw": 55
        },
        "64kt_wind_nm": {
          "ne": 35,
          "se": 60,
          "sw": 55,
          "nw": 30
        }
      },
      {
        "date": "20180524",
        "time_utc": "1800",
        "record": null,
        "status": "CY",
        "lat": 14.9,
        "lng": 54.9,
        "max_wind_kt": 80,
        "min_pressure_mb": 963,
        "34kt_wind_nm": {
          "ne": 170,
          "se": 190,
          "sw": 200,
          "nw": 135
        },
        "50kt_wind_nm": {
          "ne": 75,
          "se": 90,
          "sw": 80,
          "nw": 55
        },
        "64kt_wind_nm": {
          "ne": 35,
          "se": 45,
          "sw": 35,
          "nw": 25
        }
      },
      {
        "date": "20180525",
        "time_utc": "0000",
        "record": null,
        "status": "CY",
        "lat": 15.2,
        "lng": 54.7,
        "max_wind_kt": 85,
        "min_pressure_mb": 964,
        "34kt_wind_nm": {
          "ne": 165,
          "se": 175,
          "sw": 155,
          "nw": 125
        },
        "50kt_wind_nm": {
          "ne": 90,
          "se": 95,
          "sw": 85,
          "nw": 65
        },
        "64kt_wind_nm": {
          "ne": 50,
          "se": 50,
          "sw": 45,
          "nw": 35
        }
      },
      {
        "date": "20180525",
        "time_utc": "0600",
        "record": null,
        "status": "CY",
        "lat": 15.7,
        "lng": 54.6,
        "max_wind_kt": 90,
        "min_pressure_mb": 960,
        "34kt_wind_nm": {
          "ne": 155,
          "se": 185,
          "sw": 165,
          "nw": 125
        },
        "50kt_wind_nm": {
          "ne": 70,
          "se": 75,
          "sw": 65,
          "nw": 50
        },
        "64kt_wind_nm": {
          "ne": 40,
          "se": 45,
          "sw": 35,
          "nw": 25
        }
      },
      {
        "date": "20180525",
        "time_utc": "1200",
        "record": null,
        "status": "CY",
        "lat": 16.3,
        "lng": 54.4,
        "max_wind_kt": 100,
        "min_pressure_mb": 948,
        "34kt_wind_nm": {
          "ne": 130,
          "se": 175,
          "sw": 165,
          "nw": 110
        },
        "50kt_wind_nm": {
          "ne": 70,
          "se": 95,
          "sw": 90,
          "nw": 55
        },
        "64kt_wind_nm": {
          "ne": 35,
          "se": 50,
          "sw": 50,
          "nw": 30
        }
      },
      {
        "date": "20180525",
        "time_utc": "1800",
        "record": null,
        "status": "CY",
        "lat": 16.7,
        "lng": 53.9,
        "max_wind_kt": 100,
        "min_pressure_mb": 953,
        "34kt_wind_nm": {
          "ne": 105,
          "se": 100,
          "sw": 80,
          "nw": 95
        },
        "50kt_wind_nm": {
          "ne": 35,
          "se": 50,
          "sw": 40,
          "nw": 45
        },
        "64kt_wind_nm": {
          "ne": 20,
          "se": 25,
          "sw": 20,
          "nw": 25
        }
      },
      {
        "date": "20180526",
        "time_utc": "0000",
        "record": "L",
        "status": "CY",
        "lat": 17.2,
        "lng": 53.5,
        "max_wind_kt": 85,
        "min_pressure_mb": 963,
        "34kt_wind_nm": {
          "ne": 120,
          "se": 190,
          "sw": 90,
          "nw": 85
        },
        "50kt_wind_nm": {
          "ne": 60,
          "se": 105,
          "sw": 45,
          "nw": 40
        },
        "64kt_wind_nm": {
          "ne": 30,
          "se": 55,
          "sw": 20,
          "nw": 20
        }
      },
      {
        "date": "20180526",
        "time_utc": "0600",
        "record": null,
        "status": "CY",
        "lat": 17.9,
        "lng": 53.3,
        "max_wind_kt": 70,
        "min_pressure_mb": 970,
        "34kt_wind_nm": {
          "ne": 120,
          "se": 150,
          "sw": 90,
          "nw": 85
        },
        "50kt_wind_nm": {
          "ne": 60,
          "se": 70,
          "sw": 45,
          "nw": 40
        },
        "64kt_wind_nm": {
          "ne": 10,
          "se": 10,
          "sw": 10,
          "nw": 10
        }
      },
      {
        "date": "20180526",
        "time_utc": "1200",
        "record": null,
        "status": "TS",
        "lat": 18.6,
        "lng": 53.1,
        "max_wind_kt": 55,
        "min_pressure_mb": 982,
        "34kt_wind_nm": {
          "ne": 120,
          "se": 190,
          "sw": 90,
          "nw": 85
        },
        "50kt_wind_nm": {
          "ne": 60,
          "se": 105,
          "sw": 45,
          "nw": 40
        },
        "64kt_wind_nm": {
          "ne": 0,
          "se": 0,
          "sw": 0,
          "nw": 0
        }
      },
      {
        "date": "20180526",
        "time_utc": "1800",
        "record": null,
        "status": "TS",
        "lat": 18.9,
        "lng": 52.7,
        "max_wind_kt": 45,
        "min_pressure_mb": 989,
        "34kt_wind_nm": {
          "ne": 80,
          "se": 80,
          "sw": 80,
          "nw": 80
        },
        "50kt_wind_nm": {
          "ne": 0,
          "se": 0,
          "sw": 0,
          "nw": 0
        },
        "64kt_wind_nm": {
          "ne": 0,
          "se": 0,
          "sw": 0,
          "nw": 0
        }
      },
      {
        "date": "20180527",
        "time_utc": "0000",
        "record": null,
        "status": "TS",
        "lat": 19,
        "lng": 52.3,
        "max_wind_kt": 35,
        "min_pressure_mb": 996,
        "34kt_wind_nm": {
          "ne": 65,
          "se": 65,
          "sw": 65,
          "nw": 65
        },
        "50kt_wind_nm": {
          "ne": 0,
          "se": 0,
          "sw": 0,
          "nw": 0
        },
        "64kt_wind_nm": {
          "ne": 0,
          "se": 0,
          "sw": 0,
          "nw": 0
        }
      },
      {
        "date": "20180527",
        "time_utc": "0600",
        "record": null,
        "status": "TD",
        "lat": 19,
        "lng": 52,
        "max_wind_kt": 30,
        "min_pressure_mb": 1000,
        "34kt_wind_nm": {
          "ne": 0,
          "se": 0,
          "sw": 0,
          "nw": 0
        },
        "50kt_wind_nm": {
          "ne": 0,
          "se": 0,
          "sw": 0,
          "nw": 0
        },
        "64kt_wind_nm": {
          "ne": 0,
          "se": 0,
          "sw": 0,
          "nw": 0
        }
      }
    ]
  },
  {
    "id": "IO032018_Three",
    "dead_or_missing": 0,
    "cost_usd": 0,
    "retired": false,
    "data": [
      {
        "date": "20180528",
        "time_utc": "0000",
        "record": null,
        "status": "DB",
        "lat": 16.5,
        "lng": 90.2,
        "max_wind_kt": 20,
        "min_pressure_mb": 1007,
        "34kt_wind_nm": {
          "ne": 0,
          "se": 0,
          "sw": 0,
          "nw": 0
        },
        "50kt_wind_nm": {
          "ne": 0,
          "se": 0,
          "sw": 0,
          "nw": 0
        },
        "64kt_wind_nm": {
          "ne": 0,
          "se": 0,
          "sw": 0,
          "nw": 0
        }
      },
      {
        "date": "20180528",
        "time_utc": "0600",
        "record": null,
        "status": "TD",
        "lat": 16.9,
        "lng": 90.6,
        "max_wind_kt": 25,
        "min_pressure_mb": 1004,
        "34kt_wind_nm": {
          "ne": 0,
          "se": 0,
          "sw": 0,
          "nw": 0
        },
        "50kt_wind_nm": {
          "ne": 0,
          "se": 0,
          "sw": 0,
          "nw": 0
        },
        "64kt_wind_nm": {
          "ne": 0,
          "se": 0,
          "sw": 0,
          "nw": 0
        }
      },
      {
        "date": "20180528",
        "time_utc": "1200",
        "record": null,
        "status": "TD",
        "lat": 17.3,
        "lng": 91,
        "max_wind_kt": 25,
        "min_pressure_mb": 1004,
        "34kt_wind_nm": {
          "ne": 0,
          "se": 0,
          "sw": 0,
          "nw": 0
        },
        "50kt_wind_nm": {
          "ne": 0,
          "se": 0,
          "sw": 0,
          "nw": 0
        },
        "64kt_wind_nm": {
          "ne": 0,
          "se": 0,
          "sw": 0,
          "nw": 0
        }
      },
      {
        "date": "20180528",
        "time_utc": "1800",
        "record": null,
        "status": "WV",
        "lat": 17.8,
        "lng": 91.5,
        "max_wind_kt": 30,
        "min_pressure_mb": 1000,
        "34kt_wind_nm": {
          "ne": 0,
          "se": 0,
          "sw": 0,
          "nw": 0
        },
        "50kt_wind_nm": {
          "ne": 0,
          "se": 0,
          "sw": 0,
          "nw": 0
        },
        "64kt_wind_nm": {
          "ne": 0,
          "se": 0,
          "sw": 0,
          "nw": 0
        }
      },
      {
        "date": "20180529",
        "time_utc": "0000",
        "record": null,
        "status": "TS",
        "lat": 18.3,
        "lng": 92,
        "max_wind_kt": 35,
        "min_pressure_mb": 996,
        "34kt_wind_nm": {
          "ne": 0,
          "se": 185,
          "sw": 160,
          "nw": 0
        },
        "50kt_wind_nm": {
          "ne": 0,
          "se": 0,
          "sw": 0,
          "nw": 0
        },
        "64kt_wind_nm": {
          "ne": 0,
          "se": 0,
          "sw": 0,
          "nw": 0
        }
      },
      {
        "date": "20180529",
        "time_utc": "0600",
        "record": null,
        "status": "TS",
        "lat": 18.8,
        "lng": 92.6,
        "max_wind_kt": 40,
        "min_pressure_mb": 993,
        "34kt_wind_nm": {
          "ne": 120,
          "se": 180,
          "sw": 135,
          "nw": 75
        },
        "50kt_wind_nm": {
          "ne": 0,
          "se": 0,
          "sw": 0,
          "nw": 0
        },
        "64kt_wind_nm": {
          "ne": 0,
          "se": 0,
          "sw": 0,
          "nw": 0
        }
      },
      {
        "date": "20180529",
        "time_utc": "1200",
        "record": null,
        "status": "TS",
        "lat": 19.5,
        "lng": 93.5,
        "max_wind_kt": 45,
        "min_pressure_mb": 989,
        "34kt_wind_nm": {
          "ne": 110,
          "se": 185,
          "sw": 160,
          "nw": 65
        },
        "50kt_wind_nm": {
          "ne": 0,
          "se": 0,
          "sw": 0,
          "nw": 0
        },
        "64kt_wind_nm": {
          "ne": 0,
          "se": 0,
          "sw": 0,
          "nw": 0
        }
      },
      {
        "date": "20180529",
        "time_utc": "1800",
        "record": "L",
        "status": "TS",
        "lat": 20.3,
        "lng": 94.5,
        "max_wind_kt": 35,
        "min_pressure_mb": 996,
        "34kt_wind_nm": {
          "ne": 0,
          "se": 185,
          "sw": 160,
          "nw": 0
        },
        "50kt_wind_nm": {
          "ne": 0,
          "se": 0,
          "sw": 0,
          "nw": 0
        },
        "64kt_wind_nm": {
          "ne": 0,
          "se": 0,
          "sw": 0,
          "nw": 0
        }
      },
      {
        "date": "20180530",
        "time_utc": "0000",
        "record": null,
        "status": "TD",
        "lat": 21.3,
        "lng": 95.7,
        "max_wind_kt": 30,
        "min_pressure_mb": 1000,
        "34kt_wind_nm": {
          "ne": 0,
          "se": 0,
          "sw": 0,
          "nw": 0
        },
        "50kt_wind_nm": {
          "ne": 0,
          "se": 0,
          "sw": 0,
          "nw": 0
        },
        "64kt_wind_nm": {
          "ne": 0,
          "se": 0,
          "sw": 0,
          "nw": 0
        }
      }
    ]
  },
  {
    "id": "IO042018_Daye",
    "dead_or_missing": 0,
    "cost_usd": 0,
    "retired": false,
    "data": [
      {
        "date": "20180919",
        "time_utc": "1800",
        "record": null,
        "status": "TD",
        "lat": 16.9,
        "lng": 87.4,
        "max_wind_kt": 30,
        "min_pressure_mb": 1000,
        "34kt_wind_nm": {
          "ne": 0,
          "se": 0,
          "sw": 0,
          "nw": 0
        },
        "50kt_wind_nm": {
          "ne": 0,
          "se": 0,
          "sw": 0,
          "nw": 0
        },
        "64kt_wind_nm": {
          "ne": 0,
          "se": 0,
          "sw": 0,
          "nw": 0
        }
      },
      {
        "date": "20180920",
        "time_utc": "0000",
        "record": null,
        "status": "TD",
        "lat": 16.8,
        "lng": 87.2,
        "max_wind_kt": 30,
        "min_pressure_mb": 998,
        "34kt_wind_nm": {
          "ne": 0,
          "se": 0,
          "sw": 0,
          "nw": 0
        },
        "50kt_wind_nm": {
          "ne": 0,
          "se": 0,
          "sw": 0,
          "nw": 0
        },
        "64kt_wind_nm": {
          "ne": 0,
          "se": 0,
          "sw": 0,
          "nw": 0
        }
      },
      {
        "date": "20180920",
        "time_utc": "0600",
        "record": null,
        "status": "TD",
        "lat": 17.5,
        "lng": 87.2,
        "max_wind_kt": 30,
        "min_pressure_mb": 997,
        "34kt_wind_nm": {
          "ne": 0,
          "se": 0,
          "sw": 0,
          "nw": 0
        },
        "50kt_wind_nm": {
          "ne": 0,
          "se": 0,
          "sw": 0,
          "nw": 0
        },
        "64kt_wind_nm": {
          "ne": 0,
          "se": 0,
          "sw": 0,
          "nw": 0
        }
      },
      {
        "date": "20180920",
        "time_utc": "1200",
        "record": null,
        "status": "TS",
        "lat": 18.2,
        "lng": 86.4,
        "max_wind_kt": 35,
        "min_pressure_mb": 995,
        "34kt_wind_nm": {
          "ne": 65,
          "se": 85,
          "sw": 85,
          "nw": 65
        },
        "50kt_wind_nm": {
          "ne": 0,
          "se": 0,
          "sw": 0,
          "nw": 0
        },
        "64kt_wind_nm": {
          "ne": 0,
          "se": 0,
          "sw": 0,
          "nw": 0
        }
      },
      {
        "date": "20180920",
        "time_utc": "1800",
        "record": null,
        "status": "TS",
        "lat": 18.9,
        "lng": 85.3,
        "max_wind_kt": 35,
        "min_pressure_mb": 999,
        "34kt_wind_nm": {
          "ne": 55,
          "se": 50,
          "sw": 50,
          "nw": 0
        },
        "50kt_wind_nm": {
          "ne": 0,
          "se": 0,
          "sw": 0,
          "nw": 0
        },
        "64kt_wind_nm": {
          "ne": 0,
          "se": 0,
          "sw": 0,
          "nw": 0
        }
      },
      {
        "date": "20180921",
        "time_utc": "0000",
        "record": "L",
        "status": "TS",
        "lat": 19.5,
        "lng": 83.4,
        "max_wind_kt": 35,
        "min_pressure_mb": 996,
        "34kt_wind_nm": {
          "ne": 50,
          "se": 0,
          "sw": 0,
          "nw": 0
        },
        "50kt_wind_nm": {
          "ne": 0,
          "se": 0,
          "sw": 0,
          "nw": 0
        },
        "64kt_wind_nm": {
          "ne": 0,
          "se": 0,
          "sw": 0,
          "nw": 0
        }
      },
      {
        "date": "20180921",
        "time_utc": "0600",
        "record": null,
        "status": "TD",
        "lat": 19.8,
        "lng": 81.7,
        "max_wind_kt": 30,
        "min_pressure_mb": 1000,
        "34kt_wind_nm": {
          "ne": 0,
          "se": 0,
          "sw": 0,
          "nw": 0
        },
        "50kt_wind_nm": {
          "ne": 0,
          "se": 0,
          "sw": 0,
          "nw": 0
        },
        "64kt_wind_nm": {
          "ne": 0,
          "se": 0,
          "sw": 0,
          "nw": 0
        }
      },
      {
        "date": "20180921",
        "time_utc": "1200",
        "record": null,
        "status": "TD",
        "lat": 20.6,
        "lng": 79.6,
        "max_wind_kt": 25,
        "min_pressure_mb": 1004,
        "34kt_wind_nm": {
          "ne": 0,
          "se": 0,
          "sw": 0,
          "nw": 0
        },
        "50kt_wind_nm": {
          "ne": 0,
          "se": 0,
          "sw": 0,
          "nw": 0
        },
        "64kt_wind_nm": {
          "ne": 0,
          "se": 0,
          "sw": 0,
          "nw": 0
        }
      }
    ]
  },
  {
    "id": "IO052018_Luban",
    "dead_or_missing": 14,
    "cost_usd": 1000000000,
    "retired": false,
    "data": [
      {
        "date": "20181005",
        "time_utc": "1800",
        "record": null,
        "status": "DB",
        "lat": 11.2,
        "lng": 68.9,
        "max_wind_kt": 20,
        "min_pressure_mb": 1004,
        "34kt_wind_nm": {
          "ne": 0,
          "se": 0,
          "sw": 0,
          "nw": 0
        },
        "50kt_wind_nm": {
          "ne": 0,
          "se": 0,
          "sw": 0,
          "nw": 0
        },
        "64kt_wind_nm": {
          "ne": 0,
          "se": 0,
          "sw": 0,
          "nw": 0
        }
      },
      {
        "date": "20181006",
        "time_utc": "0000",
        "record": null,
        "status": "DB",
        "lat": 11,
        "lng": 67.9,
        "max_wind_kt": 20,
        "min_pressure_mb": 1007,
        "34kt_wind_nm": {
          "ne": 0,
          "se": 0,
          "sw": 0,
          "nw": 0
        },
        "50kt_wind_nm": {
          "ne": 0,
          "se": 0,
          "sw": 0,
          "nw": 0
        },
        "64kt_wind_nm": {
          "ne": 0,
          "se": 0,
          "sw": 0,
          "nw": 0
        }
      },
      {
        "date": "20181006",
        "time_utc": "0600",
        "record": null,
        "status": "TD",
        "lat": 11,
        "lng": 67.1,
        "max_wind_kt": 25,
        "min_pressure_mb": 1006,
        "34kt_wind_nm": {
          "ne": 0,
          "se": 0,
          "sw": 0,
          "nw": 0
        },
        "50kt_wind_nm": {
          "ne": 0,
          "se": 0,
          "sw": 0,
          "nw": 0
        },
        "64kt_wind_nm": {
          "ne": 0,
          "se": 0,
          "sw": 0,
          "nw": 0
        }
      },
      {
        "date": "20181006",
        "time_utc": "1200",
        "record": null,
        "status": "TD",
        "lat": 11,
        "lng": 66.7,
        "max_wind_kt": 25,
        "min_pressure_mb": 1004,
        "34kt_wind_nm": {
          "ne": 0,
          "se": 0,
          "sw": 0,
          "nw": 0
        },
        "50kt_wind_nm": {
          "ne": 0,
          "se": 0,
          "sw": 0,
          "nw": 0
        },
        "64kt_wind_nm": {
          "ne": 0,
          "se": 0,
          "sw": 0,
          "nw": 0
        }
      },
      {
        "date": "20181006",
        "time_utc": "1800",
        "record": null,
        "status": "TD",
        "lat": 11.1,
        "lng": 66.3,
        "max_wind_kt": 25,
        "min_pressure_mb": 1004,
        "34kt_wind_nm": {
          "ne": 0,
          "se": 0,
          "sw": 0,
          "nw": 0
        },
        "50kt_wind_nm": {
          "ne": 0,
          "se": 0,
          "sw": 0,
          "nw": 0
        },
        "64kt_wind_nm": {
          "ne": 0,
          "se": 0,
          "sw": 0,
          "nw": 0
        }
      },
      {
        "date": "20181007",
        "time_utc": "0000",
        "record": null,
        "status": "TD",
        "lat": 11.2,
        "lng": 66.1,
        "max_wind_kt": 25,
        "min_pressure_mb": 1003,
        "34kt_wind_nm": {
          "ne": 0,
          "se": 0,
          "sw": 0,
          "nw": 0
        },
        "50kt_wind_nm": {
          "ne": 0,
          "se": 0,
          "sw": 0,
          "nw": 0
        },
        "64kt_wind_nm": {
          "ne": 0,
          "se": 0,
          "sw": 0,
          "nw": 0
        }
      },
      {
        "date": "20181007",
        "time_utc": "0600",
        "record": null,
        "status": "TD",
        "lat": 11.5,
        "lng": 65.2,
        "max_wind_kt": 25,
        "min_pressure_mb": 1004,
        "34kt_wind_nm": {
          "ne": 0,
          "se": 0,
          "sw": 0,
          "nw": 0
        },
        "50kt_wind_nm": {
          "ne": 0,
          "se": 0,
          "sw": 0,
          "nw": 0
        },
        "64kt_wind_nm": {
          "ne": 0,
          "se": 0,
          "sw": 0,
          "nw": 0
        }
      },
      {
        "date": "20181007",
        "time_utc": "1200",
        "record": null,
        "status": "TD",
        "lat": 11.8,
        "lng": 64.3,
        "max_wind_kt": 30,
        "min_pressure_mb": 1000,
        "34kt_wind_nm": {
          "ne": 0,
          "se": 0,
          "sw": 0,
          "nw": 0
        },
        "50kt_wind_nm": {
          "ne": 0,
          "se": 0,
          "sw": 0,
          "nw": 0
        },
        "64kt_wind_nm": {
          "ne": 0,
          "se": 0,
          "sw": 0,
          "nw": 0
        }
      },
      {
        "date": "20181007",
        "time_utc": "1800",
        "record": null,
        "status": "TS",
        "lat": 11.8,
        "lng": 63.4,
        "max_wind_kt": 35,
        "min_pressure_mb": 996,
        "34kt_wind_nm": {
          "ne": 130,
          "se": 130,
          "sw": 120,
          "nw": 120
        },
        "50kt_wind_nm": {
          "ne": 0,
          "se": 0,
          "sw": 0,
          "nw": 0
        },
        "64kt_wind_nm": {
          "ne": 0,
          "se": 0,
          "sw": 0,
          "nw": 0
        }
      },
      {
        "date": "20181008",
        "time_utc": "0000",
        "record": null,
        "status": "TS",
        "lat": 11.8,
        "lng": 62.6,
        "max_wind_kt": 40,
        "min_pressure_mb": 993,
        "34kt_wind_nm": {
          "ne": 120,
          "se": 120,
          "sw": 110,
          "nw": 110
        },
        "50kt_wind_nm": {
          "ne": 0,
          "se": 0,
          "sw": 0,
          "nw": 0
        },
        "64kt_wind_nm": {
          "ne": 0,
          "se": 0,
          "sw": 0,
          "nw": 0
        }
      },
      {
        "date": "20181008",
        "time_utc": "0600",
        "record": null,
        "status": "TS",
        "lat": 11.9,
        "lng": 61.9,
        "max_wind_kt": 45,
        "min_pressure_mb": 989,
        "34kt_wind_nm": {
          "ne": 145,
          "se": 120,
          "sw": 120,
          "nw": 105
        },
        "50kt_wind_nm": {
          "ne": 0,
          "se": 0,
          "sw": 0,
          "nw": 0
        },
        "64kt_wind_nm": {
          "ne": 0,
          "se": 0,
          "sw": 0,
          "nw": 0
        }
      },
      {
        "date": "20181008",
        "time_utc": "1200",
        "record": null,
        "status": "TS",
        "lat": 12.2,
        "lng": 61.6,
        "max_wind_kt": 50,
        "min_pressure_mb": 985,
        "34kt_wind_nm": {
          "ne": 150,
          "se": 105,
          "sw": 120,
          "nw": 130
        },
        "50kt_wind_nm": {
          "ne": 0,
          "se": 0,
          "sw": 35,
          "nw": 40
        },
        "64kt_wind_nm": {
          "ne": 0,
          "se": 0,
          "sw": 0,
          "nw": 0
        }
      },
      {
        "date": "20181008",
        "time_utc": "1800",
        "record": null,
        "status": "TS",
        "lat": 12.4,
        "lng": 61.2,
        "max_wind_kt": 55,
        "min_pressure_mb": 982,
        "34kt_wind_nm": {
          "ne": 140,
          "se": 125,
          "sw": 150,
          "nw": 120
        },
        "50kt_wind_nm": {
          "ne": 35,
          "se": 35,
          "sw": 40,
          "nw": 50
        },
        "64kt_wind_nm": {
          "ne": 0,
          "se": 0,
          "sw": 0,
          "nw": 0
        }
      },
      {
        "date": "20181009",
        "time_utc": "0000",
        "record": null,
        "status": "TS",
        "lat": 12.7,
        "lng": 60.8,
        "max_wind_kt": 55,
        "min_pressure_mb": 982,
        "34kt_wind_nm": {
          "ne": 125,
          "se": 125,
          "sw": 135,
          "nw": 110
        },
        "50kt_wind_nm": {
          "ne": 50,
          "se": 50,
          "sw": 40,
          "nw": 35
        },
        "64kt_wind_nm": {
          "ne": 0,
          "se": 0,
          "sw": 0,
          "nw": 0
        }
      },
      {
        "date": "20181009",
        "time_utc": "0600",
        "record": null,
        "status": "TS",
        "lat": 12.9,
        "lng": 60.6,
        "max_wind_kt": 60,
        "min_pressure_mb": 978,
        "34kt_wind_nm": {
          "ne": 115,
          "se": 125,
          "sw": 140,
          "nw": 95
        },
        "50kt_wind_nm": {
          "ne": 45,
          "se": 30,
          "sw": 35,
          "nw": 45
        },
        "64kt_wind_nm": {
          "ne": 0,
          "se": 0,
          "sw": 0,
          "nw": 0
        }
      },
      {
        "date": "20181009",
        "time_utc": "1200",
        "record": null,
        "status": "TS",
        "lat": 13.1,
        "lng": 60.4,
        "max_wind_kt": 60,
        "min_pressure_mb": 978,
        "34kt_wind_nm": {
          "ne": 115,
          "se": 130,
          "sw": 145,
          "nw": 120
        },
        "50kt_wind_nm": {
          "ne": 40,
          "se": 55,
          "sw": 55,
          "nw": 50
        },
        "64kt_wind_nm": {
          "ne": 0,
          "se": 0,
          "sw": 0,
          "nw": 0
        }
      },
      {
        "date": "20181009",
        "time_utc": "1800",
        "record": null,
        "status": "CY",
        "lat": 13.7,
        "lng": 59.8,
        "max_wind_kt": 65,
        "min_pressure_mb": 974,
        "34kt_wind_nm": {
          "ne": 120,
          "se": 125,
          "sw": 135,
          "nw": 115
        },
        "50kt_wind_nm": {
          "ne": 60,
          "se": 65,
          "sw": 60,
          "nw": 60
        },
        "64kt_wind_nm": {
          "ne": 20,
          "se": 15,
          "sw": 20,
          "nw": 20
        }
      },
      {
        "date": "20181010",
        "time_utc": "0000",
        "record": null,
        "status": "CY",
        "lat": 13.9,
        "lng": 59.3,
        "max_wind_kt": 70,
        "min_pressure_mb": 970,
        "34kt_wind_nm": {
          "ne": 125,
          "se": 125,
          "sw": 130,
          "nw": 120
        },
        "50kt_wind_nm": {
          "ne": 65,
          "se": 65,
          "sw": 60,
          "nw": 60
        },
        "64kt_wind_nm": {
          "ne": 30,
          "se": 25,
          "sw": 25,
          "nw": 30
        }
      },
      {
        "date": "20181010",
        "time_utc": "0600",
        "record": null,
        "status": "CY",
        "lat": 14.2,
        "lng": 59,
        "max_wind_kt": 75,
        "min_pressure_mb": 967,
        "34kt_wind_nm": {
          "ne": 140,
          "se": 130,
          "sw": 140,
          "nw": 130
        },
        "50kt_wind_nm": {
          "ne": 75,
          "se": 105,
          "sw": 95,
          "nw": 80
        },
        "64kt_wind_nm": {
          "ne": 40,
          "se": 55,
          "sw": 50,
          "nw": 40
        }
      },
      {
        "date": "20181010",
        "time_utc": "1200",
        "record": null,
        "status": "CY",
        "lat": 14.4,
        "lng": 58.6,
        "max_wind_kt": 85,
        "min_pressure_mb": 969,
        "34kt_wind_nm": {
          "ne": 125,
          "se": 125,
          "sw": 115,
          "nw": 120
        },
        "50kt_wind_nm": {
          "ne": 65,
          "se": 65,
          "sw": 60,
          "nw": 60
        },
        "64kt_wind_nm": {
          "ne": 35,
          "se": 35,
          "sw": 30,
          "nw": 30
        }
      },
      {
        "date": "20181010",
        "time_utc": "1800",
        "record": null,
        "status": "CY",
        "lat": 14.4,
        "lng": 58.4,
        "max_wind_kt": 85,
        "min_pressure_mb": 959,
        "34kt_wind_nm": {
          "ne": 135,
          "se": 110,
          "sw": 130,
          "nw": 120
        },
        "50kt_wind_nm": {
          "ne": 70,
          "se": 70,
          "sw": 70,
          "nw": 65
        },
        "64kt_wind_nm": {
          "ne": 30,
          "se": 35,
          "sw": 35,
          "nw": 35
        }
      },
      {
        "date": "20181011",
        "time_utc": "0000",
        "record": null,
        "status": "CY",
        "lat": 14.4,
        "lng": 58.2,
        "max_wind_kt": 75,
        "min_pressure_mb": 975,
        "34kt_wind_nm": {
          "ne": 135,
          "se": 130,
          "sw": 115,
          "nw": 120
        },
        "50kt_wind_nm": {
          "ne": 70,
          "se": 70,
          "sw": 60,
          "nw": 60
        },
        "64kt_wind_nm": {
          "ne": 40,
          "se": 35,
          "sw": 30,
          "nw": 35
        }
      },
      {
        "date": "20181011",
        "time_utc": "0600",
        "record": null,
        "status": "CY",
        "lat": 14.4,
        "lng": 58,
        "max_wind_kt": 70,
        "min_pressure_mb": 982,
        "34kt_wind_nm": {
          "ne": 125,
          "se": 90,
          "sw": 115,
          "nw": 120
        },
        "50kt_wind_nm": {
          "ne": 50,
          "se": 45,
          "sw": 50,
          "nw": 50
        },
        "64kt_wind_nm": {
          "ne": 25,
          "se": 20,
          "sw": 25,
          "nw": 25
        }
      },
      {
        "date": "20181011",
        "time_utc": "1200",
        "record": null,
        "status": "TS",
        "lat": 14.5,
        "lng": 57.9,
        "max_wind_kt": 60,
        "min_pressure_mb": 978,
        "34kt_wind_nm": {
          "ne": 120,
          "se": 100,
          "sw": 115,
          "nw": 120
        },
        "50kt_wind_nm": {
          "ne": 45,
          "se": 40,
          "sw": 35,
          "nw": 45
        },
        "64kt_wind_nm": {
          "ne": 0,
          "se": 0,
          "sw": 0,
          "nw": 0
        }
      },
      {
        "date": "20181011",
        "time_utc": "1800",
        "record": null,
        "status": "TS",
        "lat": 14.6,
        "lng": 57.8,
        "max_wind_kt": 50,
        "min_pressure_mb": 985,
        "34kt_wind_nm": {
          "ne": 105,
          "se": 95,
          "sw": 125,
          "nw": 115
        },
        "50kt_wind_nm": {
          "ne": 55,
          "se": 40,
          "sw": 35,
          "nw": 45
        },
        "64kt_wind_nm": {
          "ne": 0,
          "se": 0,
          "sw": 0,
          "nw": 0
        }
      },
      {
        "date": "20181012",
        "time_utc": "0000",
        "record": null,
        "status": "TS",
        "lat": 14.6,
        "lng": 57.6,
        "max_wind_kt": 45,
        "min_pressure_mb": 989,
        "34kt_wind_nm": {
          "ne": 100,
          "se": 90,
          "sw": 110,
          "nw": 105
        },
        "50kt_wind_nm": {
          "ne": 0,
          "se": 0,
          "sw": 0,
          "nw": 0
        },
        "64kt_wind_nm": {
          "ne": 0,
          "se": 0,
          "sw": 0,
          "nw": 0
        }
      },
      {
        "date": "20181012",
        "time_utc": "0600",
        "record": null,
        "status": "TS",
        "lat": 14.6,
        "lng": 57.4,
        "max_wind_kt": 40,
        "min_pressure_mb": 993,
        "34kt_wind_nm": {
          "ne": 95,
          "se": 95,
          "sw": 70,
          "nw": 100
        },
        "50kt_wind_nm": {
          "ne": 0,
          "se": 0,
          "sw": 0,
          "nw": 0
        },
        "64kt_wind_nm": {
          "ne": 0,
          "se": 0,
          "sw": 0,
          "nw": 0
        }
      },
      {
        "date": "20181012",
        "time_utc": "1200",
        "record": null,
        "status": "TS",
        "lat": 14.6,
        "lng": 56.9,
        "max_wind_kt": 40,
        "min_pressure_mb": 993,
        "34kt_wind_nm": {
          "ne": 95,
          "se": 90,
          "sw": 75,
          "nw": 110
        },
        "50kt_wind_nm": {
          "ne": 0,
          "se": 0,
          "sw": 0,
          "nw": 0
        },
        "64kt_wind_nm": {
          "ne": 0,
          "se": 0,
          "sw": 0,
          "nw": 0
        }
      },
      {
        "date": "20181012",
        "time_utc": "1800",
        "record": null,
        "status": "TS",
        "lat": 14.7,
        "lng": 56.4,
        "max_wind_kt": 40,
        "min_pressure_mb": 993,
        "34kt_wind_nm": {
          "ne": 80,
          "se": 80,
          "sw": 65,
          "nw": 100
        },
        "50kt_wind_nm": {
          "ne": 0,
          "se": 0,
          "sw": 0,
          "nw": 0
        },
        "64kt_wind_nm": {
          "ne": 0,
          "se": 0,
          "sw": 0,
          "nw": 0
        }
      },
      {
        "date": "20181013",
        "time_utc": "0000",
        "record": null,
        "status": "TS",
        "lat": 14.7,
        "lng": 55.8,
        "max_wind_kt": 40,
        "min_pressure_mb": 993,
        "34kt_wind_nm": {
          "ne": 75,
          "se": 70,
          "sw": 60,
          "nw": 90
        },
        "50kt_wind_nm": {
          "ne": 0,
          "se": 0,
          "sw": 0,
          "nw": 0
        },
        "64kt_wind_nm": {
          "ne": 0,
          "se": 0,
          "sw": 0,
          "nw": 0
        }
      },
      {
        "date": "20181013",
        "time_utc": "0600",
        "record": null,
        "status": "TS",
        "lat": 14.8,
        "lng": 55.3,
        "max_wind_kt": 40,
        "min_pressure_mb": 993,
        "34kt_wind_nm": {
          "ne": 75,
          "se": 85,
          "sw": 80,
          "nw": 105
        },
        "50kt_wind_nm": {
          "ne": 0,
          "se": 0,
          "sw": 0,
          "nw": 0
        },
        "64kt_wind_nm": {
          "ne": 0,
          "se": 0,
          "sw": 0,
          "nw": 0
        }
      },
      {
        "date": "20181013",
        "time_utc": "1200",
        "record": null,
        "status": "TS",
        "lat": 14.9,
        "lng": 54.6,
        "max_wind_kt": 40,
        "min_pressure_mb": 993,
        "34kt_wind_nm": {
          "ne": 85,
          "se": 95,
          "sw": 80,
          "nw": 100
        },
        "50kt_wind_nm": {
          "ne": 0,
          "se": 0,
          "sw": 0,
          "nw": 0
        },
        "64kt_wind_nm": {
          "ne": 0,
          "se": 0,
          "sw": 0,
          "nw": 0
        }
      },
      {
        "date": "20181013",
        "time_utc": "1800",
        "record": null,
        "status": "TS",
        "lat": 15.1,
        "lng": 53.7,
        "max_wind_kt": 40,
        "min_pressure_mb": 993,
        "34kt_wind_nm": {
          "ne": 90,
          "se": 80,
          "sw": 65,
          "nw": 85
        },
        "50kt_wind_nm": {
          "ne": 0,
          "se": 0,
          "sw": 0,
          "nw": 0
        },
        "64kt_wind_nm": {
          "ne": 0,
          "se": 0,
          "sw": 0,
          "nw": 0
        }
      },
      {
        "date": "20181014",
        "time_utc": "0000",
        "record": null,
        "status": "TS",
        "lat": 15.5,
        "lng": 52.8,
        "max_wind_kt": 35,
        "min_pressure_mb": 1002,
        "34kt_wind_nm": {
          "ne": 65,
          "se": 60,
          "sw": 45,
          "nw": 70
        },
        "50kt_wind_nm": {
          "ne": 0,
          "se": 0,
          "sw": 0,
          "nw": 0
        },
        "64kt_wind_nm": {
          "ne": 0,
          "se": 0,
          "sw": 0,
          "nw": 0
        }
      },
      {
        "date": "20181014",
        "time_utc": "0600",
        "record": "L",
        "status": "TS",
        "lat": 15.8,
        "lng": 52.2,
        "max_wind_kt": 35,
        "min_pressure_mb": 996,
        "34kt_wind_nm": {
          "ne": 70,
          "se": 60,
          "sw": 70,
          "nw": 60
        },
        "50kt_wind_nm": {
          "ne": 0,
          "se": 0,
          "sw": 0,
          "nw": 0
        },
        "64kt_wind_nm": {
          "ne": 0,
          "se": 0,
          "sw": 0,
          "nw": 0
        }
      },
      {
        "date": "20181014",
        "time_utc": "1200",
        "record": null,
        "status": "TD",
        "lat": 16.2,
        "lng": 51.6,
        "max_wind_kt": 30,
        "min_pressure_mb": 1000,
        "34kt_wind_nm": {
          "ne": 0,
          "se": 0,
          "sw": 0,
          "nw": 0
        },
        "50kt_wind_nm": {
          "ne": 0,
          "se": 0,
          "sw": 0,
          "nw": 0
        },
        "64kt_wind_nm": {
          "ne": 0,
          "se": 0,
          "sw": 0,
          "nw": 0
        }
      },
      {
        "date": "20181014",
        "time_utc": "1800",
        "record": null,
        "status": "TD",
        "lat": 16.5,
        "lng": 51,
        "max_wind_kt": 25,
        "min_pressure_mb": 1004,
        "34kt_wind_nm": {
          "ne": 0,
          "se": 0,
          "sw": 0,
          "nw": 0
        },
        "50kt_wind_nm": {
          "ne": 0,
          "se": 0,
          "sw": 0,
          "nw": 0
        },
        "64kt_wind_nm": {
          "ne": 0,
          "se": 0,
          "sw": 0,
          "nw": 0
        }
      }
    ]
  },
  {
    "id": "IO062018_Titli",
    "dead_or_missing": 89,
    "cost_usd": 920000000,
    "retired": false,
    "data": [
      {
        "date": "20181008",
        "time_utc": "0000",
        "record": null,
        "status": "DB",
        "lat": 14.2,
        "lng": 88.4,
        "max_wind_kt": 20,
        "min_pressure_mb": 1007,
        "34kt_wind_nm": {
          "ne": 0,
          "se": 0,
          "sw": 0,
          "nw": 0
        },
        "50kt_wind_nm": {
          "ne": 0,
          "se": 0,
          "sw": 0,
          "nw": 0
        },
        "64kt_wind_nm": {
          "ne": 0,
          "se": 0,
          "sw": 0,
          "nw": 0
        }
      },
      {
        "date": "20181008",
        "time_utc": "0600",
        "record": null,
        "status": "TD",
        "lat": 14.2,
        "lng": 88,
        "max_wind_kt": 25,
        "min_pressure_mb": 1005,
        "34kt_wind_nm": {
          "ne": 0,
          "se": 0,
          "sw": 0,
          "nw": 0
        },
        "50kt_wind_nm": {
          "ne": 0,
          "se": 0,
          "sw": 0,
          "nw": 0
        },
        "64kt_wind_nm": {
          "ne": 0,
          "se": 0,
          "sw": 0,
          "nw": 0
        }
      },
      {
        "date": "20181008",
        "time_utc": "1200",
        "record": null,
        "status": "TD",
        "lat": 14.3,
        "lng": 87.6,
        "max_wind_kt": 30,
        "min_pressure_mb": 1002,
        "34kt_wind_nm": {
          "ne": 0,
          "se": 0,
          "sw": 0,
          "nw": 0
        },
        "50kt_wind_nm": {
          "ne": 0,
          "se": 0,
          "sw": 0,
          "nw": 0
        },
        "64kt_wind_nm": {
          "ne": 0,
          "se": 0,
          "sw": 0,
          "nw": 0
        }
      },
      {
        "date": "20181008",
        "time_utc": "1800",
        "record": null,
        "status": "TD",
        "lat": 14.4,
        "lng": 87.3,
        "max_wind_kt": 30,
        "min_pressure_mb": 1000,
        "34kt_wind_nm": {
          "ne": 0,
          "se": 0,
          "sw": 0,
          "nw": 0
        },
        "50kt_wind_nm": {
          "ne": 0,
          "se": 0,
          "sw": 0,
          "nw": 0
        },
        "64kt_wind_nm": {
          "ne": 0,
          "se": 0,
          "sw": 0,
          "nw": 0
        }
      },
      {
        "date": "20181009",
        "time_utc": "0000",
        "record": null,
        "status": "TS",
        "lat": 14.6,
        "lng": 87.1,
        "max_wind_kt": 35,
        "min_pressure_mb": 996,
        "34kt_wind_nm": {
          "ne": 105,
          "se": 125,
          "sw": 120,
          "nw": 110
        },
        "50kt_wind_nm": {
          "ne": 0,
          "se": 0,
          "sw": 0,
          "nw": 0
        },
        "64kt_wind_nm": {
          "ne": 0,
          "se": 0,
          "sw": 0,
          "nw": 0
        }
      },
      {
        "date": "20181009",
        "time_utc": "0600",
        "record": null,
        "status": "TS",
        "lat": 14.8,
        "lng": 86.9,
        "max_wind_kt": 40,
        "min_pressure_mb": 993,
        "34kt_wind_nm": {
          "ne": 65,
          "se": 45,
          "sw": 60,
          "nw": 80
        },
        "50kt_wind_nm": {
          "ne": 0,
          "se": 0,
          "sw": 0,
          "nw": 0
        },
        "64kt_wind_nm": {
          "ne": 0,
          "se": 0,
          "sw": 0,
          "nw": 0
        }
      },
      {
        "date": "20181009",
        "time_utc": "1200",
        "record": null,
        "status": "TS",
        "lat": 15.1,
        "lng": 86.8,
        "max_wind_kt": 45,
        "min_pressure_mb": 997,
        "34kt_wind_nm": {
          "ne": 90,
          "se": 150,
          "sw": 120,
          "nw": 100
        },
        "50kt_wind_nm": {
          "ne": 0,
          "se": 0,
          "sw": 0,
          "nw": 0
        },
        "64kt_wind_nm": {
          "ne": 0,
          "se": 0,
          "sw": 0,
          "nw": 0
        }
      },
      {
        "date": "20181009",
        "time_utc": "1800",
        "record": null,
        "status": "TS",
        "lat": 15.6,
        "lng": 86.6,
        "max_wind_kt": 50,
        "min_pressure_mb": 985,
        "34kt_wind_nm": {
          "ne": 110,
          "se": 125,
          "sw": 60,
          "nw": 70
        },
        "50kt_wind_nm": {
          "ne": 0,
          "se": 45,
          "sw": 0,
          "nw": 0
        },
        "64kt_wind_nm": {
          "ne": 0,
          "se": 0,
          "sw": 0,
          "nw": 0
        }
      },
      {
        "date": "20181010",
        "time_utc": "0000",
        "record": null,
        "status": "CY",
        "lat": 16.1,
        "lng": 86.2,
        "max_wind_kt": 65,
        "min_pressure_mb": 974,
        "34kt_wind_nm": {
          "ne": 120,
          "se": 110,
          "sw": 80,
          "nw": 105
        },
        "50kt_wind_nm": {
          "ne": 60,
          "se": 55,
          "sw": 35,
          "nw": 50
        },
        "64kt_wind_nm": {
          "ne": 30,
          "se": 30,
          "sw": 20,
          "nw": 25
        }
      },
      {
        "date": "20181010",
        "time_utc": "0600",
        "record": null,
        "status": "CY",
        "lat": 16.9,
        "lng": 85.7,
        "max_wind_kt": 75,
        "min_pressure_mb": 976,
        "34kt_wind_nm": {
          "ne": 130,
          "se": 115,
          "sw": 85,
          "nw": 100
        },
        "50kt_wind_nm": {
          "ne": 70,
          "se": 60,
          "sw": 40,
          "nw": 60
        },
        "64kt_wind_nm": {
          "ne": 40,
          "se": 25,
          "sw": 20,
          "nw": 30
        }
      },
      {
        "date": "20181010",
        "time_utc": "1200",
        "record": null,
        "status": "CY",
        "lat": 17.6,
        "lng": 85.3,
        "max_wind_kt": 90,
        "min_pressure_mb": 956,
        "34kt_wind_nm": {
          "ne": 155,
          "se": 150,
          "sw": 115,
          "nw": 125
        },
        "50kt_wind_nm": {
          "ne": 85,
          "se": 80,
          "sw": 60,
          "nw": 65
        },
        "64kt_wind_nm": {
          "ne": 45,
          "se": 45,
          "sw": 30,
          "nw": 35
        }
      },
      {
        "date": "20181010",
        "time_utc": "1800",
        "record": null,
        "status": "CY",
        "lat": 18.3,
        "lng": 84.8,
        "max_wind_kt": 105,
        "min_pressure_mb": 944,
        "34kt_wind_nm": {
          "ne": 120,
          "se": 135,
          "sw": 120,
          "nw": 95
        },
        "50kt_wind_nm": {
          "ne": 65,
          "se": 75,
          "sw": 70,
          "nw": 50
        },
        "64kt_wind_nm": {
          "ne": 40,
          "se": 40,
          "sw": 30,
          "nw": 25
        }
      },
      {
        "date": "20181011",
        "time_utc": "0000",
        "record": "L",
        "status": "CY",
        "lat": 18.7,
        "lng": 84.3,
        "max_wind_kt": 100,
        "min_pressure_mb": 948,
        "34kt_wind_nm": {
          "ne": 150,
          "se": 130,
          "sw": 115,
          "nw": 95
        },
        "50kt_wind_nm": {
          "ne": 80,
          "se": 70,
          "sw": 60,
          "nw": 45
        },
        "64kt_wind_nm": {
          "ne": 45,
          "se": 35,
          "sw": 30,
          "nw": 25
        }
      },
      {
        "date": "20181011",
        "time_utc": "0600",
        "record": null,
        "status": "CY",
        "lat": 19,
        "lng": 83.9,
        "max_wind_kt": 80,
        "min_pressure_mb": 963,
        "34kt_wind_nm": {
          "ne": 150,
          "se": 130,
          "sw": 100,
          "nw": 85
        },
        "50kt_wind_nm": {
          "ne": 65,
          "se": 75,
          "sw": 50,
          "nw": 40
        },
        "64kt_wind_nm": {
          "ne": 30,
          "se": 35,
          "sw": 25,
          "nw": 20
        }
      },
      {
        "date": "20181011",
        "time_utc": "1200",
        "record": null,
        "status": "CY",
        "lat": 19.5,
        "lng": 83.8,
        "max_wind_kt": 65,
        "min_pressure_mb": 974,
        "34kt_wind_nm": {
          "ne": 140,
          "se": 115,
          "sw": 90,
          "nw": 70
        },
        "50kt_wind_nm": {
          "ne": 60,
          "se": 60,
          "sw": 40,
          "nw": 30
        },
        "64kt_wind_nm": {
          "ne": 25,
          "se": 25,
          "sw": 20,
          "nw": 20
        }
      },
      {
        "date": "20181011",
        "time_utc": "1800",
        "record": null,
        "status": "TS",
        "lat": 19.9,
        "lng": 84.1,
        "max_wind_kt": 55,
        "min_pressure_mb": 982,
        "34kt_wind_nm": {
          "ne": 75,
          "se": 75,
          "sw": 75,
          "nw": 70
        },
        "50kt_wind_nm": {
          "ne": 0,
          "se": 0,
          "sw": 0,
          "nw": 0
        },
        "64kt_wind_nm": {
          "ne": 0,
          "se": 0,
          "sw": 0,
          "nw": 0
        }
      },
      {
        "date": "20181012",
        "time_utc": "0000",
        "record": null,
        "status": "TS",
        "lat": 20.6,
        "lng": 84.7,
        "max_wind_kt": 40,
        "min_pressure_mb": 993,
        "34kt_wind_nm": {
          "ne": 75,
          "se": 65,
          "sw": 75,
          "nw": 70
        },
        "50kt_wind_nm": {
          "ne": 0,
          "se": 0,
          "sw": 0,
          "nw": 0
        },
        "64kt_wind_nm": {
          "ne": 0,
          "se": 0,
          "sw": 0,
          "nw": 0
        }
      },
      {
        "date": "20181012",
        "time_utc": "0600",
        "record": null,
        "status": "TD",
        "lat": 21.3,
        "lng": 85.5,
        "max_wind_kt": 30,
        "min_pressure_mb": 1000,
        "34kt_wind_nm": {
          "ne": 0,
          "se": 0,
          "sw": 0,
          "nw": 0
        },
        "50kt_wind_nm": {
          "ne": 0,
          "se": 0,
          "sw": 0,
          "nw": 0
        },
        "64kt_wind_nm": {
          "ne": 0,
          "se": 0,
          "sw": 0,
          "nw": 0
        }
      }
    ]
  },
  {
    "id": "IO072018_Gaja",
    "dead_or_missing": 52,
    "cost_usd": 775000000,
    "retired": false,
    "data": [
      {
        "date": "20181110",
        "time_utc": "1200",
        "record": null,
        "status": "DB",
        "lat": 12.9,
        "lng": 90.2,
        "max_wind_kt": 30,
        "min_pressure_mb": 1004,
        "34kt_wind_nm": {
          "ne": 0,
          "se": 0,
          "sw": 0,
          "nw": 0
        },
        "50kt_wind_nm": {
          "ne": 0,
          "se": 0,
          "sw": 0,
          "nw": 0
        },
        "64kt_wind_nm": {
          "ne": 0,
          "se": 0,
          "sw": 0,
          "nw": 0
        }
      },
      {
        "date": "20181110",
        "time_utc": "1800",
        "record": null,
        "status": "TS",
        "lat": 13.2,
        "lng": 89.7,
        "max_wind_kt": 35,
        "min_pressure_mb": 1000,
        "34kt_wind_nm": {
          "ne": 55,
          "se": 20,
          "sw": 30,
          "nw": 30
        },
        "50kt_wind_nm": {
          "ne": 0,
          "se": 0,
          "sw": 0,
          "nw": 0
        },
        "64kt_wind_nm": {
          "ne": 0,
          "se": 0,
          "sw": 0,
          "nw": 0
        }
      },
      {
        "date": "20181111",
        "time_utc": "0000",
        "record": null,
        "status": "TS",
        "lat": 13.3,
        "lng": 89.1,
        "max_wind_kt": 35,
        "min_pressure_mb": 996,
        "34kt_wind_nm": {
          "ne": 60,
          "se": 20,
          "sw": 30,
          "nw": 55
        },
        "50kt_wind_nm": {
          "ne": 0,
          "se": 0,
          "sw": 0,
          "nw": 0
        },
        "64kt_wind_nm": {
          "ne": 0,
          "se": 0,
          "sw": 0,
          "nw": 0
        }
      },
      {
        "date": "20181111",
        "time_utc": "0600",
        "record": null,
        "status": "TS",
        "lat": 13.4,
        "lng": 88.4,
        "max_wind_kt": 35,
        "min_pressure_mb": 996,
        "34kt_wind_nm": {
          "ne": 45,
          "se": 45,
          "sw": 40,
          "nw": 40
        },
        "50kt_wind_nm": {
          "ne": 0,
          "se": 0,
          "sw": 0,
          "nw": 0
        },
        "64kt_wind_nm": {
          "ne": 0,
          "se": 0,
          "sw": 0,
          "nw": 0
        }
      },
      {
        "date": "20181111",
        "time_utc": "1200",
        "record": null,
        "status": "TS",
        "lat": 13.1,
        "lng": 87.4,
        "max_wind_kt": 35,
        "min_pressure_mb": 996,
        "34kt_wind_nm": {
          "ne": 55,
          "se": 35,
          "sw": 35,
          "nw": 45
        },
        "50kt_wind_nm": {
          "ne": 0,
          "se": 0,
          "sw": 0,
          "nw": 0
        },
        "64kt_wind_nm": {
          "ne": 0,
          "se": 0,
          "sw": 0,
          "nw": 0
        }
      },
      {
        "date": "20181111",
        "time_utc": "1800",
        "record": null,
        "status": "TS",
        "lat": 12.8,
        "lng": 87.2,
        "max_wind_kt": 35,
        "min_pressure_mb": 1004,
        "34kt_wind_nm": {
          "ne": 65,
          "se": 35,
          "sw": 40,
          "nw": 40
        },
        "50kt_wind_nm": {
          "ne": 0,
          "se": 0,
          "sw": 0,
          "nw": 0
        },
        "64kt_wind_nm": {
          "ne": 0,
          "se": 0,
          "sw": 0,
          "nw": 0
        }
      },
      {
        "date": "20181112",
        "time_utc": "0000",
        "record": null,
        "status": "TS",
        "lat": 12.5,
        "lng": 87.3,
        "max_wind_kt": 35,
        "min_pressure_mb": 1004,
        "34kt_wind_nm": {
          "ne": 50,
          "se": 30,
          "sw": 35,
          "nw": 45
        },
        "50kt_wind_nm": {
          "ne": 0,
          "se": 0,
          "sw": 0,
          "nw": 0
        },
        "64kt_wind_nm": {
          "ne": 0,
          "se": 0,
          "sw": 0,
          "nw": 0
        }
      },
      {
        "date": "20181112",
        "time_utc": "0600",
        "record": null,
        "status": "TS",
        "lat": 12.3,
        "lng": 87.6,
        "max_wind_kt": 35,
        "min_pressure_mb": 996,
        "34kt_wind_nm": {
          "ne": 55,
          "se": 30,
          "sw": 30,
          "nw": 55
        },
        "50kt_wind_nm": {
          "ne": 0,
          "se": 0,
          "sw": 0,
          "nw": 0
        },
        "64kt_wind_nm": {
          "ne": 0,
          "se": 0,
          "sw": 0,
          "nw": 0
        }
      },
      {
        "date": "20181112",
        "time_utc": "1200",
        "record": null,
        "status": "TD",
        "lat": 12.9,
        "lng": 87.8,
        "max_wind_kt": 30,
        "min_pressure_mb": 1000,
        "34kt_wind_nm": {
          "ne": 0,
          "se": 0,
          "sw": 0,
          "nw": 0
        },
        "50kt_wind_nm": {
          "ne": 0,
          "se": 0,
          "sw": 0,
          "nw": 0
        },
        "64kt_wind_nm": {
          "ne": 0,
          "se": 0,
          "sw": 0,
          "nw": 0
        }
      },
      {
        "date": "20181112",
        "time_utc": "1800",
        "record": null,
        "status": "TD",
        "lat": 13.4,
        "lng": 87.6,
        "max_wind_kt": 30,
        "min_pressure_mb": 1000,
        "34kt_wind_nm": {
          "ne": 0,
          "se": 0,
          "sw": 0,
          "nw": 0
        },
        "50kt_wind_nm": {
          "ne": 0,
          "se": 0,
          "sw": 0,
          "nw": 0
        },
        "64kt_wind_nm": {
          "ne": 0,
          "se": 0,
          "sw": 0,
          "nw": 0
        }
      },
      {
        "date": "20181113",
        "time_utc": "0000",
        "record": null,
        "status": "TD",
        "lat": 13.9,
        "lng": 87.2,
        "max_wind_kt": 30,
        "min_pressure_mb": 1000,
        "34kt_wind_nm": {
          "ne": 0,
          "se": 0,
          "sw": 0,
          "nw": 0
        },
        "50kt_wind_nm": {
          "ne": 0,
          "se": 0,
          "sw": 0,
          "nw": 0
        },
        "64kt_wind_nm": {
          "ne": 0,
          "se": 0,
          "sw": 0,
          "nw": 0
        }
      },
      {
        "date": "20181113",
        "time_utc": "0600",
        "record": null,
        "status": "TD",
        "lat": 13.8,
        "lng": 86.5,
        "max_wind_kt": 30,
        "min_pressure_mb": 1000,
        "34kt_wind_nm": {
          "ne": 0,
          "se": 0,
          "sw": 0,
          "nw": 0
        },
        "50kt_wind_nm": {
          "ne": 0,
          "se": 0,
          "sw": 0,
          "nw": 0
        },
        "64kt_wind_nm": {
          "ne": 0,
          "se": 0,
          "sw": 0,
          "nw": 0
        }
      },
      {
        "date": "20181113",
        "time_utc": "1200",
        "record": null,
        "status": "TD",
        "lat": 13.6,
        "lng": 86.1,
        "max_wind_kt": 30,
        "min_pressure_mb": 1000,
        "34kt_wind_nm": {
          "ne": 0,
          "se": 0,
          "sw": 0,
          "nw": 0
        },
        "50kt_wind_nm": {
          "ne": 0,
          "se": 0,
          "sw": 0,
          "nw": 0
        },
        "64kt_wind_nm": {
          "ne": 0,
          "se": 0,
          "sw": 0,
          "nw": 0
        }
      },
      {
        "date": "20181113",
        "time_utc": "1800",
        "record": null,
        "status": "TS",
        "lat": 13.4,
        "lng": 85.8,
        "max_wind_kt": 35,
        "min_pressure_mb": 1003,
        "34kt_wind_nm": {
          "ne": 55,
          "se": 90,
          "sw": 35,
          "nw": 45
        },
        "50kt_wind_nm": {
          "ne": 0,
          "se": 0,
          "sw": 0,
          "nw": 0
        },
        "64kt_wind_nm": {
          "ne": 0,
          "se": 0,
          "sw": 0,
          "nw": 0
        }
      },
      {
        "date": "20181114",
        "time_utc": "0000",
        "record": null,
        "status": "TS",
        "lat": 13.1,
        "lng": 85.4,
        "max_wind_kt": 40,
        "min_pressure_mb": 1001,
        "34kt_wind_nm": {
          "ne": 50,
          "se": 80,
          "sw": 35,
          "nw": 45
        },
        "50kt_wind_nm": {
          "ne": 0,
          "se": 0,
          "sw": 0,
          "nw": 0
        },
        "64kt_wind_nm": {
          "ne": 0,
          "se": 0,
          "sw": 0,
          "nw": 0
        }
      },
      {
        "date": "20181114",
        "time_utc": "0600",
        "record": null,
        "status": "TS",
        "lat": 12.8,
        "lng": 85.1,
        "max_wind_kt": 45,
        "min_pressure_mb": 989,
        "34kt_wind_nm": {
          "ne": 50,
          "se": 55,
          "sw": 50,
          "nw": 60
        },
        "50kt_wind_nm": {
          "ne": 0,
          "se": 0,
          "sw": 0,
          "nw": 0
        },
        "64kt_wind_nm": {
          "ne": 0,
          "se": 0,
          "sw": 0,
          "nw": 0
        }
      },
      {
        "date": "20181114",
        "time_utc": "1200",
        "record": null,
        "status": "TS",
        "lat": 12.3,
        "lng": 84.5,
        "max_wind_kt": 50,
        "min_pressure_mb": 985,
        "34kt_wind_nm": {
          "ne": 45,
          "se": 50,
          "sw": 50,
          "nw": 55
        },
        "50kt_wind_nm": {
          "ne": 0,
          "se": 0,
          "sw": 0,
          "nw": 0
        },
        "64kt_wind_nm": {
          "ne": 0,
          "se": 0,
          "sw": 0,
          "nw": 0
        }
      },
      {
        "date": "20181114",
        "time_utc": "1800",
        "record": null,
        "status": "TS",
        "lat": 12,
        "lng": 83.9,
        "max_wind_kt": 50,
        "min_pressure_mb": 985,
        "34kt_wind_nm": {
          "ne": 55,
          "se": 30,
          "sw": 30,
          "nw": 35
        },
        "50kt_wind_nm": {
          "ne": 0,
          "se": 0,
          "sw": 0,
          "nw": 0
        },
        "64kt_wind_nm": {
          "ne": 0,
          "se": 0,
          "sw": 0,
          "nw": 0
        }
      },
      {
        "date": "20181115",
        "time_utc": "0000",
        "record": null,
        "status": "TS",
        "lat": 11.6,
        "lng": 83.1,
        "max_wind_kt": 55,
        "min_pressure_mb": 982,
        "34kt_wind_nm": {
          "ne": 50,
          "se": 35,
          "sw": 35,
          "nw": 40
        },
        "50kt_wind_nm": {
          "ne": 0,
          "se": 0,
          "sw": 0,
          "nw": 0
        },
        "64kt_wind_nm": {
          "ne": 0,
          "se": 0,
          "sw": 0,
          "nw": 0
        }
      },
      {
        "date": "20181115",
        "time_utc": "0600",
        "record": null,
        "status": "CY",
        "lat": 11.3,
        "lng": 82.3,
        "max_wind_kt": 65,
        "min_pressure_mb": 974,
        "34kt_wind_nm": {
          "ne": 65,
          "se": 55,
          "sw": 75,
          "nw": 65
        },
        "50kt_wind_nm": {
          "ne": 20,
          "se": 15,
          "sw": 25,
          "nw": 35
        },
        "64kt_wind_nm": {
          "ne": 0,
          "se": 0,
          "sw": 0,
          "nw": 0
        }
      },
      {
        "date": "20181115",
        "time_utc": "1200",
        "record": null,
        "status": "CY",
        "lat": 10.9,
        "lng": 81.2,
        "max_wind_kt": 70,
        "min_pressure_mb": 970,
        "34kt_wind_nm": {
          "ne": 65,
          "se": 50,
          "sw": 55,
          "nw": 65
        },
        "50kt_wind_nm": {
          "ne": 30,
          "se": 25,
          "sw": 25,
          "nw": 30
        },
        "64kt_wind_nm": {
          "ne": 20,
          "se": 20,
          "sw": 20,
          "nw": 20
        }
      },
      {
        "date": "20181115",
        "time_utc": "1800",
        "record": null,
        "status": "CY",
        "lat": 10.6,
        "lng": 80.2,
        "max_wind_kt": 80,
        "min_pressure_mb": 963,
        "34kt_wind_nm": {
          "ne": 45,
          "se": 55,
          "sw": 45,
          "nw": 60
        },
        "50kt_wind_nm": {
          "ne": 15,
          "se": 25,
          "sw": 20,
          "nw": 15
        },
        "64kt_wind_nm": {
          "ne": 5,
          "se": 10,
          "sw": 5,
          "nw": 5
        }
      },
      {
        "date": "20181116",
        "time_utc": "0000",
        "record": "L",
        "status": "CY",
        "lat": 10.5,
        "lng": 79.1,
        "max_wind_kt": 70,
        "min_pressure_mb": 970,
        "34kt_wind_nm": {
          "ne": 70,
          "se": 50,
          "sw": 45,
          "nw": 60
        },
        "50kt_wind_nm": {
          "ne": 35,
          "se": 20,
          "sw": 20,
          "nw": 30
        },
        "64kt_wind_nm": {
          "ne": 20,
          "se": 10,
          "sw": 10,
          "nw": 15
        }
      },
      {
        "date": "20181116",
        "time_utc": "0600",
        "record": null,
        "status": "TS",
        "lat": 10.4,
        "lng": 77.7,
        "max_wind_kt": 55,
        "min_pressure_mb": 982,
        "34kt_wind_nm": {
          "ne": 40,
          "se": 30,
          "sw": 35,
          "nw": 40
        },
        "50kt_wind_nm": {
          "ne": 15,
          "se": 5,
          "sw": 10,
          "nw": 10
        },
        "64kt_wind_nm": {
          "ne": 0,
          "se": 0,
          "sw": 0,
          "nw": 0
        }
      },
      {
        "date": "20181116",
        "time_utc": "1200",
        "record": null,
        "status": "TS",
        "lat": 10,
        "lng": 76.2,
        "max_wind_kt": 45,
        "min_pressure_mb": 989,
        "34kt_wind_nm": {
          "ne": 40,
          "se": 25,
          "sw": 40,
          "nw": 25
        },
        "50kt_wind_nm": {
          "ne": 0,
          "se": 0,
          "sw": 0,
          "nw": 0
        },
        "64kt_wind_nm": {
          "ne": 0,
          "se": 0,
          "sw": 0,
          "nw": 0
        }
      },
      {
        "date": "20181116",
        "time_utc": "1800",
        "record": null,
        "status": "TS",
        "lat": 9.7,
        "lng": 75.2,
        "max_wind_kt": 40,
        "min_pressure_mb": 993,
        "34kt_wind_nm": {
          "ne": 35,
          "se": 45,
          "sw": 40,
          "nw": 35
        },
        "50kt_wind_nm": {
          "ne": 0,
          "se": 0,
          "sw": 0,
          "nw": 0
        },
        "64kt_wind_nm": {
          "ne": 0,
          "se": 0,
          "sw": 0,
          "nw": 0
        }
      },
      {
        "date": "20181117",
        "time_utc": "0000",
        "record": null,
        "status": "TS",
        "lat": 9.6,
        "lng": 74,
        "max_wind_kt": 40,
        "min_pressure_mb": 1004,
        "34kt_wind_nm": {
          "ne": 40,
          "se": 20,
          "sw": 40,
          "nw": 35
        },
        "50kt_wind_nm": {
          "ne": 0,
          "se": 0,
          "sw": 0,
          "nw": 0
        },
        "64kt_wind_nm": {
          "ne": 0,
          "se": 0,
          "sw": 0,
          "nw": 0
        }
      },
      {
        "date": "20181117",
        "time_utc": "0600",
        "record": null,
        "status": "TS",
        "lat": 9.8,
        "lng": 72.8,
        "max_wind_kt": 40,
        "min_pressure_mb": 1005,
        "34kt_wind_nm": {
          "ne": 40,
          "se": 30,
          "sw": 30,
          "nw": 40
        },
        "50kt_wind_nm": {
          "ne": 0,
          "se": 0,
          "sw": 0,
          "nw": 0
        },
        "64kt_wind_nm": {
          "ne": 0,
          "se": 0,
          "sw": 0,
          "nw": 0
        }
      },
      {
        "date": "20181117",
        "time_utc": "1200",
        "record": null,
        "status": "TS",
        "lat": 10,
        "lng": 71.9,
        "max_wind_kt": 40,
        "min_pressure_mb": 1003,
        "34kt_wind_nm": {
          "ne": 40,
          "se": 30,
          "sw": 30,
          "nw": 40
        },
        "50kt_wind_nm": {
          "ne": 0,
          "se": 0,
          "sw": 0,
          "nw": 0
        },
        "64kt_wind_nm": {
          "ne": 0,
          "se": 0,
          "sw": 0,
          "nw": 0
        }
      },
      {
        "date": "20181117",
        "time_utc": "1800",
        "record": null,
        "status": "TS",
        "lat": 10.3,
        "lng": 70.9,
        "max_wind_kt": 35,
        "min_pressure_mb": 1007,
        "34kt_wind_nm": {
          "ne": 35,
          "se": 25,
          "sw": 25,
          "nw": 35
        },
        "50kt_wind_nm": {
          "ne": 0,
          "se": 0,
          "sw": 0,
          "nw": 0
        },
        "64kt_wind_nm": {
          "ne": 0,
          "se": 0,
          "sw": 0,
          "nw": 0
        }
      },
      {
        "date": "20181118",
        "time_utc": "0000",
        "record": null,
        "status": "TD",
        "lat": 10.5,
        "lng": 70,
        "max_wind_kt": 30,
        "min_pressure_mb": 1006,
        "34kt_wind_nm": {
          "ne": 0,
          "se": 0,
          "sw": 0,
          "nw": 0
        },
        "50kt_wind_nm": {
          "ne": 0,
          "se": 0,
          "sw": 0,
          "nw": 0
        },
        "64kt_wind_nm": {
          "ne": 0,
          "se": 0,
          "sw": 0,
          "nw": 0
        }
      },
      {
        "date": "20181118",
        "time_utc": "0600",
        "record": null,
        "status": "TD",
        "lat": 10.5,
        "lng": 69.1,
        "max_wind_kt": 25,
        "min_pressure_mb": 1009,
        "34kt_wind_nm": {
          "ne": 0,
          "se": 0,
          "sw": 0,
          "nw": 0
        },
        "50kt_wind_nm": {
          "ne": 0,
          "se": 0,
          "sw": 0,
          "nw": 0
        },
        "64kt_wind_nm": {
          "ne": 0,
          "se": 0,
          "sw": 0,
          "nw": 0
        }
      },
      {
        "date": "20181118",
        "time_utc": "1200",
        "record": null,
        "status": "DB",
        "lat": 10.5,
        "lng": 68.4,
        "max_wind_kt": 20,
        "min_pressure_mb": 1008,
        "34kt_wind_nm": {
          "ne": 0,
          "se": 0,
          "sw": 0,
          "nw": 0
        },
        "50kt_wind_nm": {
          "ne": 0,
          "se": 0,
          "sw": 0,
          "nw": 0
        },
        "64kt_wind_nm": {
          "ne": 0,
          "se": 0,
          "sw": 0,
          "nw": 0
        }
      },
      {
        "date": "20181118",
        "time_utc": "1800",
        "record": null,
        "status": "DB",
        "lat": 10.5,
        "lng": 67.5,
        "max_wind_kt": 20,
        "min_pressure_mb": 1010,
        "34kt_wind_nm": {
          "ne": 0,
          "se": 0,
          "sw": 0,
          "nw": 0
        },
        "50kt_wind_nm": {
          "ne": 0,
          "se": 0,
          "sw": 0,
          "nw": 0
        },
        "64kt_wind_nm": {
          "ne": 0,
          "se": 0,
          "sw": 0,
          "nw": 0
        }
      },
      {
        "date": "20181119",
        "time_utc": "0000",
        "record": null,
        "status": "DB",
        "lat": 10.5,
        "lng": 66.7,
        "max_wind_kt": 20,
        "min_pressure_mb": 1010,
        "34kt_wind_nm": {
          "ne": 0,
          "se": 0,
          "sw": 0,
          "nw": 0
        },
        "50kt_wind_nm": {
          "ne": 0,
          "se": 0,
          "sw": 0,
          "nw": 0
        },
        "64kt_wind_nm": {
          "ne": 0,
          "se": 0,
          "sw": 0,
          "nw": 0
        }
      },
      {
        "date": "20181119",
        "time_utc": "0600",
        "record": null,
        "status": "DB",
        "lat": 10.5,
        "lng": 65.9,
        "max_wind_kt": 20,
        "min_pressure_mb": 1010,
        "34kt_wind_nm": {
          "ne": 0,
          "se": 0,
          "sw": 0,
          "nw": 0
        },
        "50kt_wind_nm": {
          "ne": 0,
          "se": 0,
          "sw": 0,
          "nw": 0
        },
        "64kt_wind_nm": {
          "ne": 0,
          "se": 0,
          "sw": 0,
          "nw": 0
        }
      }
    ]
  },
  {
    "id": "IO082018_Phethai",
    "dead_or_missing": 8,
    "cost_usd": 100000000,
    "retired": false,
    "data": [
      {
        "date": "20181213",
        "time_utc": "1200",
        "record": null,
        "status": "TD",
        "lat": 6.9,
        "lng": 88.9,
        "max_wind_kt": 30,
        "min_pressure_mb": 1000,
        "34kt_wind_nm": {
          "ne": 0,
          "se": 0,
          "sw": 0,
          "nw": 0
        },
        "50kt_wind_nm": {
          "ne": 0,
          "se": 0,
          "sw": 0,
          "nw": 0
        },
        "64kt_wind_nm": {
          "ne": 0,
          "se": 0,
          "sw": 0,
          "nw": 0
        }
      },
      {
        "date": "20181213",
        "time_utc": "1800",
        "record": null,
        "status": "TD",
        "lat": 7.4,
        "lng": 88.1,
        "max_wind_kt": 30,
        "min_pressure_mb": 1000,
        "34kt_wind_nm": {
          "ne": 0,
          "se": 0,
          "sw": 0,
          "nw": 0
        },
        "50kt_wind_nm": {
          "ne": 0,
          "se": 0,
          "sw": 0,
          "nw": 0
        },
        "64kt_wind_nm": {
          "ne": 0,
          "se": 0,
          "sw": 0,
          "nw": 0
        }
      },
      {
        "date": "20181214",
        "time_utc": "0000",
        "record": null,
        "status": "TD",
        "lat": 7.6,
        "lng": 87.7,
        "max_wind_kt": 30,
        "min_pressure_mb": 1000,
        "34kt_wind_nm": {
          "ne": 0,
          "se": 0,
          "sw": 0,
          "nw": 0
        },
        "50kt_wind_nm": {
          "ne": 0,
          "se": 0,
          "sw": 0,
          "nw": 0
        },
        "64kt_wind_nm": {
          "ne": 0,
          "se": 0,
          "sw": 0,
          "nw": 0
        }
      },
      {
        "date": "20181214",
        "time_utc": "0600",
        "record": null,
        "status": "TD",
        "lat": 7.8,
        "lng": 87.3,
        "max_wind_kt": 30,
        "min_pressure_mb": 1000,
        "34kt_wind_nm": {
          "ne": 0,
          "se": 0,
          "sw": 0,
          "nw": 0
        },
        "50kt_wind_nm": {
          "ne": 0,
          "se": 0,
          "sw": 0,
          "nw": 0
        },
        "64kt_wind_nm": {
          "ne": 0,
          "se": 0,
          "sw": 0,
          "nw": 0
        }
      },
      {
        "date": "20181214",
        "time_utc": "1200",
        "record": null,
        "status": "TD",
        "lat": 8,
        "lng": 86.8,
        "max_wind_kt": 30,
        "min_pressure_mb": 1000,
        "34kt_wind_nm": {
          "ne": 0,
          "se": 0,
          "sw": 0,
          "nw": 0
        },
        "50kt_wind_nm": {
          "ne": 0,
          "se": 0,
          "sw": 0,
          "nw": 0
        },
        "64kt_wind_nm": {
          "ne": 0,
          "se": 0,
          "sw": 0,
          "nw": 0
        }
      },
      {
        "date": "20181214",
        "time_utc": "1800",
        "record": null,
        "status": "TD",
        "lat": 8.5,
        "lng": 86.3,
        "max_wind_kt": 30,
        "min_pressure_mb": 1000,
        "34kt_wind_nm": {
          "ne": 0,
          "se": 0,
          "sw": 0,
          "nw": 0
        },
        "50kt_wind_nm": {
          "ne": 0,
          "se": 0,
          "sw": 0,
          "nw": 0
        },
        "64kt_wind_nm": {
          "ne": 0,
          "se": 0,
          "sw": 0,
          "nw": 0
        }
      },
      {
        "date": "20181215",
        "time_utc": "0000",
        "record": null,
        "status": "TD",
        "lat": 9,
        "lng": 85.9,
        "max_wind_kt": 30,
        "min_pressure_mb": 1000,
        "34kt_wind_nm": {
          "ne": 0,
          "se": 0,
          "sw": 0,
          "nw": 0
        },
        "50kt_wind_nm": {
          "ne": 0,
          "se": 0,
          "sw": 0,
          "nw": 0
        },
        "64kt_wind_nm": {
          "ne": 0,
          "se": 0,
          "sw": 0,
          "nw": 0
        }
      },
      {
        "date": "20181215",
        "time_utc": "0600",
        "record": null,
        "status": "TS",
        "lat": 9.7,
        "lng": 85.4,
        "max_wind_kt": 35,
        "min_pressure_mb": 996,
        "34kt_wind_nm": {
          "ne": 145,
          "se": 95,
          "sw": 95,
          "nw": 145
        },
        "50kt_wind_nm": {
          "ne": 0,
          "se": 0,
          "sw": 0,
          "nw": 0
        },
        "64kt_wind_nm": {
          "ne": 0,
          "se": 0,
          "sw": 0,
          "nw": 0
        }
      },
      {
        "date": "20181215",
        "time_utc": "1200",
        "record": null,
        "status": "TS",
        "lat": 10.1,
        "lng": 84.9,
        "max_wind_kt": 40,
        "min_pressure_mb": 993,
        "34kt_wind_nm": {
          "ne": 155,
          "se": 75,
          "sw": 130,
          "nw": 195
        },
        "50kt_wind_nm": {
          "ne": 0,
          "se": 0,
          "sw": 0,
          "nw": 0
        },
        "64kt_wind_nm": {
          "ne": 0,
          "se": 0,
          "sw": 0,
          "nw": 0
        }
      },
      {
        "date": "20181215",
        "time_utc": "1800",
        "record": null,
        "status": "TS",
        "lat": 10.6,
        "lng": 84.5,
        "max_wind_kt": 45,
        "min_pressure_mb": 989,
        "34kt_wind_nm": {
          "ne": 110,
          "se": 70,
          "sw": 130,
          "nw": 195
        },
        "50kt_wind_nm": {
          "ne": 0,
          "se": 0,
          "sw": 0,
          "nw": 0
        },
        "64kt_wind_nm": {
          "ne": 0,
          "se": 0,
          "sw": 0,
          "nw": 0
        }
      },
      {
        "date": "20181216",
        "time_utc": "0000",
        "record": null,
        "status": "TS",
        "lat": 11.4,
        "lng": 84.3,
        "max_wind_kt": 45,
        "min_pressure_mb": 989,
        "34kt_wind_nm": {
          "ne": 120,
          "se": 45,
          "sw": 80,
          "nw": 110
        },
        "50kt_wind_nm": {
          "ne": 0,
          "se": 0,
          "sw": 0,
          "nw": 0
        },
        "64kt_wind_nm": {
          "ne": 0,
          "se": 0,
          "sw": 0,
          "nw": 0
        }
      },
      {
        "date": "20181216",
        "time_utc": "0600",
        "record": null,
        "status": "TS",
        "lat": 12.3,
        "lng": 83.9,
        "max_wind_kt": 50,
        "min_pressure_mb": 997,
        "34kt_wind_nm": {
          "ne": 125,
          "se": 90,
          "sw": 65,
          "nw": 110
        },
        "50kt_wind_nm": {
          "ne": 45,
          "se": 45,
          "sw": 45,
          "nw": 45
        },
        "64kt_wind_nm": {
          "ne": 0,
          "se": 0,
          "sw": 0,
          "nw": 0
        }
      },
      {
        "date": "20181216",
        "time_utc": "1200",
        "record": null,
        "status": "TS",
        "lat": 13.4,
        "lng": 83.1,
        "max_wind_kt": 55,
        "min_pressure_mb": 994,
        "34kt_wind_nm": {
          "ne": 130,
          "se": 85,
          "sw": 85,
          "nw": 155
        },
        "50kt_wind_nm": {
          "ne": 65,
          "se": 40,
          "sw": 40,
          "nw": 65
        },
        "64kt_wind_nm": {
          "ne": 0,
          "se": 0,
          "sw": 0,
          "nw": 0
        }
      },
      {
        "date": "20181216",
        "time_utc": "1800",
        "record": null,
        "status": "TS",
        "lat": 14.1,
        "lng": 82.8,
        "max_wind_kt": 55,
        "min_pressure_mb": 996,
        "34kt_wind_nm": {
          "ne": 170,
          "se": 90,
          "sw": 70,
          "nw": 130
        },
        "50kt_wind_nm": {
          "ne": 90,
          "se": 40,
          "sw": 30,
          "nw": 65
        },
        "64kt_wind_nm": {
          "ne": 0,
          "se": 0,
          "sw": 0,
          "nw": 0
        }
      },
      {
        "date": "20181217",
        "time_utc": "0000",
        "record": null,
        "status": "TS",
        "lat": 14.8,
        "lng": 82.6,
        "max_wind_kt": 50,
        "min_pressure_mb": 995,
        "34kt_wind_nm": {
          "ne": 125,
          "se": 100,
          "sw": 60,
          "nw": 100
        },
        "50kt_wind_nm": {
          "ne": 0,
          "se": 0,
          "sw": 0,
          "nw": 0
        },
        "64kt_wind_nm": {
          "ne": 0,
          "se": 0,
          "sw": 0,
          "nw": 0
        }
      },
      {
        "date": "20181217",
        "time_utc": "0600",
        "record": null,
        "status": "TS",
        "lat": 15.8,
        "lng": 82.4,
        "max_wind_kt": 40,
        "min_pressure_mb": 1004,
        "34kt_wind_nm": {
          "ne": 80,
          "se": 75,
          "sw": 55,
          "nw": 60
        },
        "50kt_wind_nm": {
          "ne": 0,
          "se": 0,
          "sw": 0,
          "nw": 0
        },
        "64kt_wind_nm": {
          "ne": 0,
          "se": 0,
          "sw": 0,
          "nw": 0
        }
      },
      {
        "date": "20181217",
        "time_utc": "1200",
        "record": null,
        "status": "TD",
        "lat": 16.8,
        "lng": 82.5,
        "max_wind_kt": 30,
        "min_pressure_mb": 1007,
        "34kt_wind_nm": {
          "ne": 0,
          "se": 0,
          "sw": 0,
          "nw": 0
        },
        "50kt_wind_nm": {
          "ne": 0,
          "se": 0,
          "sw": 0,
          "nw": 0
        },
        "64kt_wind_nm": {
          "ne": 0,
          "se": 0,
          "sw": 0,
          "nw": 0
        }
      },
      {
        "date": "20181217",
        "time_utc": "1800",
        "record": "L",
        "status": "TD",
        "lat": 18.1,
        "lng": 83,
        "max_wind_kt": 25,
        "min_pressure_mb": 1010,
        "34kt_wind_nm": {
          "ne": 0,
          "se": 0,
          "sw": 0,
          "nw": 0
        },
        "50kt_wind_nm": {
          "ne": 0,
          "se": 0,
          "sw": 0,
          "nw": 0
        },
        "64kt_wind_nm": {
          "ne": 0,
          "se": 0,
          "sw": 0,
          "nw": 0
        }
      }
    ]
  }
]
